{
 "L": [
  {
   "is_class": false,
   "is_explicit": false,
   "module": "builtins",
   "module_short": "builtins",
   "name": "float"
  }
 ],
 "amplitude": [
  {
   "is_class": false,
   "is_explicit": false,
   "module": "builtins",
   "module_short": "builtins",
   "name": "int"
  }
 ],
 "ax": [
  {
   "is_class": false,
   "is_explicit": false,
   "module": "matplotlib.axes._axes",
   "module_short": "matplotlib.axes",
   "name": "Axes"
  },
  {
   "is_class": false,
   "is_explicit": false,
   "module": "matplotlib.axes",
   "module_short": "matplotlib.axes",
   "name": "Axes"
  },
  {
   "is_class": false,
   "is_explicit": false,
   "module": "matplotlib",
   "module_short": "matplotlib",
   "name": "Axes"
  }
 ],
 "ax.plot": [
  {
   "is_class": false,
   "is_explicit": false,
   "module": "matplotlib.axes._axes",
   "module_short": "matplotlib.axes",
   "name": "Axes.plot"
  },
  {
   "is_class": false,
   "is_explicit": false,
   "module": "matplotlib.axes",
   "module_short": "matplotlib.axes",
   "name": "Axes.plot"
  },
  {
   "is_class": false,
   "is_explicit": false,
   "module": "matplotlib",
   "module_short": "matplotlib",
   "name": "Axes.plot"
  },
  {
   "is_class": false,
   "is_explicit": false,
   "module": "matplotlib.axes._base",
   "module_short": "matplotlib.axes._base",
   "name": "_AxesBase.plot"
  },
  {
   "is_class": false,
   "is_explicit": false,
   "module": "matplotlib.axes",
   "module_short": "matplotlib.axes",
   "name": "_AxesBase.plot"
  },
  {
   "is_class": false,
   "is_explicit": false,
   "module": "matplotlib",
   "module_short": "matplotlib",
   "name": "_AxesBase.plot"
  },
  {
   "is_class": false,
   "is_explicit": false,
   "module": "matplotlib.artist",
   "module_short": "matplotlib.artist",
   "name": "Artist.plot"
  },
  {
   "is_class": false,
   "is_explicit": false,
   "module": "matplotlib",
   "module_short": "matplotlib",
   "name": "Artist.plot"
  }
 ],
 "ax.set_xlabel": [
  {
   "is_class": false,
   "is_explicit": false,
   "module": "matplotlib.axes._axes",
   "module_short": "matplotlib.axes",
   "name": "Axes.set_xlabel"
  },
  {
   "is_class": false,
   "is_explicit": false,
   "module": "matplotlib.axes",
   "module_short": "matplotlib.axes",
   "name": "Axes.set_xlabel"
  },
  {
   "is_class": false,
   "is_explicit": false,
   "module": "matplotlib",
   "module_short": "matplotlib",
   "name": "Axes.set_xlabel"
  },
  {
   "is_class": false,
   "is_explicit": false,
   "module": "matplotlib.axes._base",
   "module_short": "matplotlib.axes._base",
   "name": "_AxesBase.set_xlabel"
  },
  {
   "is_class": false,
   "is_explicit": false,
   "module": "matplotlib.axes",
   "module_short": "matplotlib.axes",
   "name": "_AxesBase.set_xlabel"
  },
  {
   "is_class": false,
   "is_explicit": false,
   "module": "matplotlib",
   "module_short": "matplotlib",
   "name": "_AxesBase.set_xlabel"
  },
  {
   "is_class": false,
   "is_explicit": false,
   "module": "matplotlib.artist",
   "module_short": "matplotlib.artist",
   "name": "Artist.set_xlabel"
  },
  {
   "is_class": false,
   "is_explicit": false,
   "module": "matplotlib",
   "module_short": "matplotlib",
   "name": "Artist.set_xlabel"
  }
 ],
 "ax.set_xlim": [
  {
   "is_class": false,
   "is_explicit": false,
   "module": "matplotlib.axes._axes",
   "module_short": "matplotlib.axes",
   "name": "Axes.set_xlim"
  },
  {
   "is_class": false,
   "is_explicit": false,
   "module": "matplotlib.axes",
   "module_short": "matplotlib.axes",
   "name": "Axes.set_xlim"
  },
  {
   "is_class": false,
   "is_explicit": false,
   "module": "matplotlib",
   "module_short": "matplotlib",
   "name": "Axes.set_xlim"
  },
  {
   "is_class": false,
   "is_explicit": false,
   "module": "matplotlib.axes._base",
   "module_short": "matplotlib.axes._base",
   "name": "_AxesBase.set_xlim"
  },
  {
   "is_class": false,
   "is_explicit": false,
   "module": "matplotlib.axes",
   "module_short": "matplotlib.axes",
   "name": "_AxesBase.set_xlim"
  },
  {
   "is_class": false,
   "is_explicit": false,
   "module": "matplotlib",
   "module_short": "matplotlib",
   "name": "_AxesBase.set_xlim"
  },
  {
   "is_class": false,
   "is_explicit": false,
   "module": "matplotlib.artist",
   "module_short": "matplotlib.artist",
   "name": "Artist.set_xlim"
  },
  {
   "is_class": false,
   "is_explicit": false,
   "module": "matplotlib",
   "module_short": "matplotlib",
   "name": "Artist.set_xlim"
  }
 ],
 "ax.set_ylabel": [
  {
   "is_class": false,
   "is_explicit": false,
   "module": "matplotlib.axes._axes",
   "module_short": "matplotlib.axes",
   "name": "Axes.set_ylabel"
  },
  {
   "is_class": false,
   "is_explicit": false,
   "module": "matplotlib.axes",
   "module_short": "matplotlib.axes",
   "name": "Axes.set_ylabel"
  },
  {
   "is_class": false,
   "is_explicit": false,
   "module": "matplotlib",
   "module_short": "matplotlib",
   "name": "Axes.set_ylabel"
  },
  {
   "is_class": false,
   "is_explicit": false,
   "module": "matplotlib.axes._base",
   "module_short": "matplotlib.axes._base",
   "name": "_AxesBase.set_ylabel"
  },
  {
   "is_class": false,
   "is_explicit": false,
   "module": "matplotlib.axes",
   "module_short": "matplotlib.axes",
   "name": "_AxesBase.set_ylabel"
  },
  {
   "is_class": false,
   "is_explicit": false,
   "module": "matplotlib",
   "module_short": "matplotlib",
   "name": "_AxesBase.set_ylabel"
  },
  {
   "is_class": false,
   "is_explicit": false,
   "module": "matplotlib.artist",
   "module_short": "matplotlib.artist",
   "name": "Artist.set_ylabel"
  },
  {
   "is_class": false,
   "is_explicit": false,
   "module": "matplotlib",
   "module_short": "matplotlib",
   "name": "Artist.set_ylabel"
  }
 ],
 "ax.set_ylim": [
  {
   "is_class": false,
   "is_explicit": false,
   "module": "matplotlib.axes._axes",
   "module_short": "matplotlib.axes",
   "name": "Axes.set_ylim"
  },
  {
   "is_class": false,
   "is_explicit": false,
   "module": "matplotlib.axes",
   "module_short": "matplotlib.axes",
   "name": "Axes.set_ylim"
  },
  {
   "is_class": false,
   "is_explicit": false,
   "module": "matplotlib",
   "module_short": "matplotlib",
   "name": "Axes.set_ylim"
  },
  {
   "is_class": false,
   "is_explicit": false,
   "module": "matplotlib.axes._base",
   "module_short": "matplotlib.axes._base",
   "name": "_AxesBase.set_ylim"
  },
  {
   "is_class": false,
   "is_explicit": false,
   "module": "matplotlib.axes",
   "module_short": "matplotlib.axes",
   "name": "_AxesBase.set_ylim"
  },
  {
   "is_class": false,
   "is_explicit": false,
   "module": "matplotlib",
   "module_short": "matplotlib",
   "name": "_AxesBase.set_ylim"
  },
  {
   "is_class": false,
   "is_explicit": false,
   "module": "matplotlib.artist",
   "module_short": "matplotlib.artist",
   "name": "Artist.set_ylim"
  },
  {
   "is_class": false,
   "is_explicit": false,
   "module": "matplotlib",
   "module_short": "matplotlib",
   "name": "Artist.set_ylim"
  }
 ],
 "axon_m": [
  {
   "is_class": false,
   "is_explicit": false,
   "module": "nrv.nmod._myelinated",
   "module_short": "nrv",
   "name": "myelinated"
  },
  {
   "is_class": false,
   "is_explicit": false,
   "module": "nrv.nmod",
   "module_short": "nrv",
   "name": "myelinated"
  },
  {
   "is_class": false,
   "is_explicit": false,
   "module": "nrv",
   "module_short": "nrv",
   "name": "myelinated"
  }
 ],
 "axon_m.insert_I_Clamp": [
  {
   "is_class": false,
   "is_explicit": false,
   "module": "nrv.nmod._myelinated",
   "module_short": "nrv",
   "name": "myelinated.insert_I_Clamp"
  },
  {
   "is_class": false,
   "is_explicit": false,
   "module": "nrv.nmod",
   "module_short": "nrv",
   "name": "myelinated.insert_I_Clamp"
  },
  {
   "is_class": false,
   "is_explicit": false,
   "module": "nrv",
   "module_short": "nrv",
   "name": "myelinated.insert_I_Clamp"
  },
  {
   "is_class": false,
   "is_explicit": false,
   "module": "nrv.nmod._axons",
   "module_short": "nrv",
   "name": "axon.insert_I_Clamp"
  },
  {
   "is_class": false,
   "is_explicit": false,
   "module": "nrv.nmod",
   "module_short": "nrv",
   "name": "axon.insert_I_Clamp"
  },
  {
   "is_class": false,
   "is_explicit": false,
   "module": "nrv",
   "module_short": "nrv",
   "name": "axon.insert_I_Clamp"
  },
  {
   "is_class": false,
   "is_explicit": false,
   "module": "nrv.backend._NRV_Simulable",
   "module_short": "nrv.backend._NRV_Simulable",
   "name": "NRV_simulable.insert_I_Clamp"
  },
  {
   "is_class": false,
   "is_explicit": false,
   "module": "nrv.backend",
   "module_short": "nrv.backend",
   "name": "NRV_simulable.insert_I_Clamp"
  },
  {
   "is_class": false,
   "is_explicit": false,
   "module": "nrv",
   "module_short": "nrv",
   "name": "NRV_simulable.insert_I_Clamp"
  },
  {
   "is_class": false,
   "is_explicit": false,
   "module": "nrv.backend._NRV_Class",
   "module_short": "nrv.backend._NRV_Class",
   "name": "NRV_class.insert_I_Clamp"
  },
  {
   "is_class": false,
   "is_explicit": false,
   "module": "nrv.backend",
   "module_short": "nrv.backend",
   "name": "NRV_class.insert_I_Clamp"
  },
  {
   "is_class": false,
   "is_explicit": false,
   "module": "nrv",
   "module_short": "nrv",
   "name": "NRV_class.insert_I_Clamp"
  }
 ],
 "axon_u": [
  {
   "is_class": false,
   "is_explicit": false,
   "module": "nrv.nmod._unmyelinated",
   "module_short": "nrv",
   "name": "unmyelinated"
  },
  {
   "is_class": false,
   "is_explicit": false,
   "module": "nrv.nmod",
   "module_short": "nrv",
   "name": "unmyelinated"
  },
  {
   "is_class": false,
   "is_explicit": false,
   "module": "nrv",
   "module_short": "nrv",
   "name": "unmyelinated"
  }
 ],
 "axon_u.insert_I_Clamp": [
  {
   "is_class": false,
   "is_explicit": false,
   "module": "nrv.nmod._unmyelinated",
   "module_short": "nrv",
   "name": "unmyelinated.insert_I_Clamp"
  },
  {
   "is_class": false,
   "is_explicit": false,
   "module": "nrv.nmod",
   "module_short": "nrv",
   "name": "unmyelinated.insert_I_Clamp"
  },
  {
   "is_class": false,
   "is_explicit": false,
   "module": "nrv",
   "module_short": "nrv",
   "name": "unmyelinated.insert_I_Clamp"
  },
  {
   "is_class": false,
   "is_explicit": false,
   "module": "nrv.nmod._axons",
   "module_short": "nrv",
   "name": "axon.insert_I_Clamp"
  },
  {
   "is_class": false,
   "is_explicit": false,
   "module": "nrv.nmod",
   "module_short": "nrv",
   "name": "axon.insert_I_Clamp"
  },
  {
   "is_class": false,
   "is_explicit": false,
   "module": "nrv",
   "module_short": "nrv",
   "name": "axon.insert_I_Clamp"
  },
  {
   "is_class": false,
   "is_explicit": false,
   "module": "nrv.backend._NRV_Simulable",
   "module_short": "nrv.backend._NRV_Simulable",
   "name": "NRV_simulable.insert_I_Clamp"
  },
  {
   "is_class": false,
   "is_explicit": false,
   "module": "nrv.backend",
   "module_short": "nrv.backend",
   "name": "NRV_simulable.insert_I_Clamp"
  },
  {
   "is_class": false,
   "is_explicit": false,
   "module": "nrv",
   "module_short": "nrv",
   "name": "NRV_simulable.insert_I_Clamp"
  },
  {
   "is_class": false,
   "is_explicit": false,
   "module": "nrv.backend._NRV_Class",
   "module_short": "nrv.backend._NRV_Class",
   "name": "NRV_class.insert_I_Clamp"
  },
  {
   "is_class": false,
   "is_explicit": false,
   "module": "nrv.backend",
   "module_short": "nrv.backend",
   "name": "NRV_class.insert_I_Clamp"
  },
  {
   "is_class": false,
   "is_explicit": false,
   "module": "nrv",
   "module_short": "nrv",
   "name": "NRV_class.insert_I_Clamp"
  }
 ],
 "axs": [
  {
   "is_class": false,
   "is_explicit": false,
   "module": "numpy",
   "module_short": "numpy",
   "name": "ndarray"
  }
 ],
 "cbar": [
  {
   "is_class": false,
   "is_explicit": false,
   "module": "matplotlib.colorbar",
   "module_short": "matplotlib.colorbar",
   "name": "Colorbar"
  },
  {
   "is_class": false,
   "is_explicit": false,
   "module": "matplotlib",
   "module_short": "matplotlib",
   "name": "Colorbar"
  }
 ],
 "cbar.set_label": [
  {
   "is_class": false,
   "is_explicit": false,
   "module": "matplotlib.colorbar",
   "module_short": "matplotlib.colorbar",
   "name": "Colorbar.set_label"
  },
  {
   "is_class": false,
   "is_explicit": false,
   "module": "matplotlib",
   "module_short": "matplotlib",
   "name": "Colorbar.set_label"
  }
 ],
 "clamp_node": [
  {
   "is_class": false,
   "is_explicit": false,
   "module": "builtins",
   "module_short": "builtins",
   "name": "int"
  }
 ],
 "d": [
  {
   "is_class": false,
   "is_explicit": false,
   "module": "builtins",
   "module_short": "builtins",
   "name": "int"
  }
 ],
 "duration": [
  {
   "is_class": false,
   "is_explicit": false,
   "module": "builtins",
   "module_short": "builtins",
   "name": "float"
  }
 ],
 "fig": [
  {
   "is_class": false,
   "is_explicit": false,
   "module": "matplotlib.figure",
   "module_short": "matplotlib.figure",
   "name": "Figure"
  },
  {
   "is_class": false,
   "is_explicit": false,
   "module": "matplotlib",
   "module_short": "matplotlib",
   "name": "Figure"
  }
 ],
 "fig.tight_layout": [
  {
   "is_class": false,
   "is_explicit": false,
   "module": "matplotlib.figure",
   "module_short": "matplotlib.figure",
   "name": "Figure.tight_layout"
  },
  {
   "is_class": false,
   "is_explicit": false,
   "module": "matplotlib",
   "module_short": "matplotlib",
   "name": "Figure.tight_layout"
  },
  {
   "is_class": false,
   "is_explicit": false,
   "module": "matplotlib.figure",
   "module_short": "matplotlib.figure",
   "name": "FigureBase.tight_layout"
  },
  {
   "is_class": false,
   "is_explicit": false,
   "module": "matplotlib",
   "module_short": "matplotlib",
   "name": "FigureBase.tight_layout"
  },
  {
   "is_class": false,
   "is_explicit": false,
   "module": "matplotlib.artist",
   "module_short": "matplotlib.artist",
   "name": "Artist.tight_layout"
  },
  {
   "is_class": false,
   "is_explicit": false,
   "module": "matplotlib",
   "module_short": "matplotlib",
   "name": "Artist.tight_layout"
  }
 ],
 "model": [
  {
   "is_class": false,
   "is_explicit": false,
   "module": "builtins",
   "module_short": "builtins",
   "name": "str"
  }
 ],
 "n_NoR": [
  {
   "is_class": false,
   "is_explicit": false,
   "module": "builtins",
   "module_short": "builtins",
   "name": "int"
  }
 ],
 "np.allclose": [
  {
   "is_class": false,
   "is_explicit": false,
   "module": "numpy",
   "module_short": "numpy",
   "name": "_ArrayFunctionDispatcher"
  },
  {
   "is_class": false,
   "is_explicit": false,
   "module": "numpy",
   "module_short": "numpy",
   "name": "allclose"
  }
 ],
 "np.max": [
  {
   "is_class": false,
   "is_explicit": false,
   "module": "numpy",
   "module_short": "numpy",
   "name": "_ArrayFunctionDispatcher"
  },
  {
   "is_class": false,
   "is_explicit": false,
   "module": "numpy",
   "module_short": "numpy",
   "name": "max"
  }
 ],
 "nrv.get_length_from_nodes": [
  {
   "is_class": false,
   "is_explicit": false,
   "module": "builtins",
   "module_short": "builtins",
   "name": "function"
  },
  {
   "is_class": false,
   "is_explicit": false,
   "module": "nrv",
   "module_short": "nrv",
   "name": "get_length_from_nodes"
  }
 ],
 "nrv.myelinated": [
  {
   "is_class": true,
   "is_explicit": false,
   "module": "nrv.nmod._myelinated",
   "module_short": "nrv",
   "name": "myelinated"
  },
  {
   "is_class": true,
   "is_explicit": false,
   "module": "nrv.nmod",
   "module_short": "nrv",
   "name": "myelinated"
  },
  {
   "is_class": true,
   "is_explicit": false,
   "module": "nrv",
   "module_short": "nrv",
   "name": "myelinated"
  },
  {
   "is_class": true,
   "is_explicit": false,
   "module": "nrv.nmod._axons",
   "module_short": "nrv",
   "name": "axon"
  },
  {
   "is_class": true,
   "is_explicit": false,
   "module": "nrv.nmod",
   "module_short": "nrv",
   "name": "axon"
  },
  {
   "is_class": true,
   "is_explicit": false,
   "module": "nrv",
   "module_short": "nrv",
   "name": "axon"
  },
  {
   "is_class": true,
   "is_explicit": false,
   "module": "nrv.backend._NRV_Simulable",
   "module_short": "nrv",
   "name": "NRV_simulable"
  },
  {
   "is_class": true,
   "is_explicit": false,
   "module": "nrv.backend",
   "module_short": "nrv",
   "name": "NRV_simulable"
  },
  {
   "is_class": true,
   "is_explicit": false,
   "module": "nrv",
   "module_short": "nrv",
   "name": "NRV_simulable"
  },
  {
   "is_class": true,
   "is_explicit": false,
   "module": "nrv.backend._NRV_Class",
   "module_short": "nrv",
   "name": "NRV_class"
  },
  {
   "is_class": true,
   "is_explicit": false,
   "module": "nrv.backend",
   "module_short": "nrv",
   "name": "NRV_class"
  },
  {
   "is_class": true,
   "is_explicit": false,
   "module": "nrv",
   "module_short": "nrv",
   "name": "NRV_class"
  },
  {
   "is_class": false,
   "is_explicit": false,
   "module": "nrv",
   "module_short": "nrv",
   "name": "myelinated"
  }
 ],
 "nrv.unmyelinated": [
  {
   "is_class": true,
   "is_explicit": false,
   "module": "nrv.nmod._unmyelinated",
   "module_short": "nrv",
   "name": "unmyelinated"
  },
  {
   "is_class": true,
   "is_explicit": false,
   "module": "nrv.nmod",
   "module_short": "nrv",
   "name": "unmyelinated"
  },
  {
   "is_class": true,
   "is_explicit": false,
   "module": "nrv",
   "module_short": "nrv",
   "name": "unmyelinated"
  },
  {
   "is_class": true,
   "is_explicit": false,
   "module": "nrv.nmod._axons",
   "module_short": "nrv",
   "name": "axon"
  },
  {
   "is_class": true,
   "is_explicit": false,
   "module": "nrv.nmod",
   "module_short": "nrv",
   "name": "axon"
  },
  {
   "is_class": true,
   "is_explicit": false,
   "module": "nrv",
   "module_short": "nrv",
   "name": "axon"
  },
  {
   "is_class": true,
   "is_explicit": false,
   "module": "nrv.backend._NRV_Simulable",
   "module_short": "nrv",
   "name": "NRV_simulable"
  },
  {
   "is_class": true,
   "is_explicit": false,
   "module": "nrv.backend",
   "module_short": "nrv",
   "name": "NRV_simulable"
  },
  {
   "is_class": true,
   "is_explicit": false,
   "module": "nrv",
   "module_short": "nrv",
   "name": "NRV_simulable"
  },
  {
   "is_class": true,
   "is_explicit": false,
   "module": "nrv.backend._NRV_Class",
   "module_short": "nrv",
   "name": "NRV_class"
  },
  {
   "is_class": true,
   "is_explicit": false,
   "module": "nrv.backend",
   "module_short": "nrv",
   "name": "NRV_class"
  },
  {
   "is_class": true,
   "is_explicit": false,
   "module": "nrv",
   "module_short": "nrv",
   "name": "NRV_class"
  },
  {
   "is_class": false,
   "is_explicit": false,
   "module": "nrv",
   "module_short": "nrv",
   "name": "unmyelinated"
  }
 ],
 "plt.show": [
  {
   "is_class": false,
   "is_explicit": false,
   "module": "builtins",
   "module_short": "builtins",
   "name": "function"
  },
  {
   "is_class": false,
   "is_explicit": false,
   "module": "matplotlib.pyplot",
   "module_short": "matplotlib.pyplot",
   "name": "show"
  }
 ],
 "plt.subplots": [
  {
   "is_class": false,
   "is_explicit": false,
   "module": "builtins",
   "module_short": "builtins",
   "name": "function"
  },
  {
   "is_class": false,
   "is_explicit": false,
   "module": "matplotlib.pyplot",
   "module_short": "matplotlib.pyplot",
   "name": "subplots"
  }
 ],
 "results": [
  {
   "is_class": false,
   "is_explicit": false,
   "module": "nrv.nmod.results._unmyelinated_results",
   "module_short": "nrv.nmod.results",
   "name": "unmyelinated_results"
  },
  {
   "is_class": false,
   "is_explicit": false,
   "module": "nrv.nmod.results",
   "module_short": "nrv.nmod.results",
   "name": "unmyelinated_results"
  },
  {
   "is_class": false,
   "is_explicit": false,
   "module": "nrv.nmod",
   "module_short": "nrv.nmod",
   "name": "unmyelinated_results"
  },
  {
   "is_class": false,
   "is_explicit": false,
   "module": "nrv",
   "module_short": "nrv",
   "name": "unmyelinated_results"
  }
 ],
 "results.V_mem": [
  {
   "is_class": false,
   "is_explicit": false,
   "module": "numpy",
   "module_short": "numpy",
   "name": "ndarray"
  }
 ],
 "results.colormap_plot": [
  {
   "is_class": false,
   "is_explicit": false,
   "module": "nrv.nmod.results._unmyelinated_results",
   "module_short": "nrv.nmod.results",
   "name": "unmyelinated_results.colormap_plot"
  },
  {
   "is_class": false,
   "is_explicit": false,
   "module": "nrv.nmod.results",
   "module_short": "nrv.nmod.results",
   "name": "unmyelinated_results.colormap_plot"
  },
  {
   "is_class": false,
   "is_explicit": false,
   "module": "nrv.nmod",
   "module_short": "nrv.nmod",
   "name": "unmyelinated_results.colormap_plot"
  },
  {
   "is_class": false,
   "is_explicit": false,
   "module": "nrv",
   "module_short": "nrv",
   "name": "unmyelinated_results.colormap_plot"
  },
  {
   "is_class": false,
   "is_explicit": false,
   "module": "nrv.nmod.results._axons_results",
   "module_short": "nrv.nmod.results",
   "name": "axon_results.colormap_plot"
  },
  {
   "is_class": false,
   "is_explicit": false,
   "module": "nrv.nmod.results",
   "module_short": "nrv.nmod.results",
   "name": "axon_results.colormap_plot"
  },
  {
   "is_class": false,
   "is_explicit": false,
   "module": "nrv.nmod",
   "module_short": "nrv.nmod",
   "name": "axon_results.colormap_plot"
  },
  {
   "is_class": false,
   "is_explicit": false,
   "module": "nrv",
   "module_short": "nrv",
   "name": "axon_results.colormap_plot"
  },
  {
   "is_class": false,
   "is_explicit": false,
   "module": "nrv.backend._NRV_Results",
   "module_short": "nrv.backend._NRV_Results",
   "name": "sim_results.colormap_plot"
  },
  {
   "is_class": false,
   "is_explicit": false,
   "module": "nrv.backend",
   "module_short": "nrv.backend",
   "name": "sim_results.colormap_plot"
  },
  {
   "is_class": false,
   "is_explicit": false,
   "module": "nrv",
   "module_short": "nrv",
   "name": "sim_results.colormap_plot"
  },
  {
   "is_class": false,
   "is_explicit": false,
   "module": "nrv.backend._NRV_Results",
   "module_short": "nrv.backend._NRV_Results",
   "name": "NRV_results.colormap_plot"
  },
  {
   "is_class": false,
   "is_explicit": false,
   "module": "nrv.backend",
   "module_short": "nrv.backend",
   "name": "NRV_results.colormap_plot"
  },
  {
   "is_class": false,
   "is_explicit": false,
   "module": "nrv",
   "module_short": "nrv",
   "name": "NRV_results.colormap_plot"
  },
  {
   "is_class": false,
   "is_explicit": false,
   "module": "nrv.backend._NRV_Class",
   "module_short": "nrv.backend._NRV_Class",
   "name": "NRV_class.colormap_plot"
  },
  {
   "is_class": false,
   "is_explicit": false,
   "module": "nrv.backend",
   "module_short": "nrv.backend",
   "name": "NRV_class.colormap_plot"
  },
  {
   "is_class": false,
   "is_explicit": false,
   "module": "nrv",
   "module_short": "nrv",
   "name": "NRV_class.colormap_plot"
  },
  {
   "is_class": false,
   "is_explicit": false,
   "module": "builtins",
   "module_short": "builtins",
   "name": "dict.colormap_plot"
  }
 ],
 "results.plot_x_t": [
  {
   "is_class": false,
   "is_explicit": false,
   "module": "nrv.nmod.results._unmyelinated_results",
   "module_short": "nrv.nmod.results",
   "name": "unmyelinated_results.plot_x_t"
  },
  {
   "is_class": false,
   "is_explicit": false,
   "module": "nrv.nmod.results",
   "module_short": "nrv.nmod.results",
   "name": "unmyelinated_results.plot_x_t"
  },
  {
   "is_class": false,
   "is_explicit": false,
   "module": "nrv.nmod",
   "module_short": "nrv.nmod",
   "name": "unmyelinated_results.plot_x_t"
  },
  {
   "is_class": false,
   "is_explicit": false,
   "module": "nrv",
   "module_short": "nrv",
   "name": "unmyelinated_results.plot_x_t"
  },
  {
   "is_class": false,
   "is_explicit": false,
   "module": "nrv.nmod.results._axons_results",
   "module_short": "nrv.nmod.results",
   "name": "axon_results.plot_x_t"
  },
  {
   "is_class": false,
   "is_explicit": false,
   "module": "nrv.nmod.results",
   "module_short": "nrv.nmod.results",
   "name": "axon_results.plot_x_t"
  },
  {
   "is_class": false,
   "is_explicit": false,
   "module": "nrv.nmod",
   "module_short": "nrv.nmod",
   "name": "axon_results.plot_x_t"
  },
  {
   "is_class": false,
   "is_explicit": false,
   "module": "nrv",
   "module_short": "nrv",
   "name": "axon_results.plot_x_t"
  },
  {
   "is_class": false,
   "is_explicit": false,
   "module": "nrv.backend._NRV_Results",
   "module_short": "nrv.backend._NRV_Results",
   "name": "sim_results.plot_x_t"
  },
  {
   "is_class": false,
   "is_explicit": false,
   "module": "nrv.backend",
   "module_short": "nrv.backend",
   "name": "sim_results.plot_x_t"
  },
  {
   "is_class": false,
   "is_explicit": false,
   "module": "nrv",
   "module_short": "nrv",
   "name": "sim_results.plot_x_t"
  },
  {
   "is_class": false,
   "is_explicit": false,
   "module": "nrv.backend._NRV_Results",
   "module_short": "nrv.backend._NRV_Results",
   "name": "NRV_results.plot_x_t"
  },
  {
   "is_class": false,
   "is_explicit": false,
   "module": "nrv.backend",
   "module_short": "nrv.backend",
   "name": "NRV_results.plot_x_t"
  },
  {
   "is_class": false,
   "is_explicit": false,
   "module": "nrv",
   "module_short": "nrv",
   "name": "NRV_results.plot_x_t"
  },
  {
   "is_class": false,
   "is_explicit": false,
   "module": "nrv.backend._NRV_Class",
   "module_short": "nrv.backend._NRV_Class",
   "name": "NRV_class.plot_x_t"
  },
  {
   "is_class": false,
   "is_explicit": false,
   "module": "nrv.backend",
   "module_short": "nrv.backend",
   "name": "NRV_class.plot_x_t"
  },
  {
   "is_class": false,
   "is_explicit": false,
   "module": "nrv",
   "module_short": "nrv",
   "name": "NRV_class.plot_x_t"
  },
  {
   "is_class": false,
   "is_explicit": false,
   "module": "builtins",
   "module_short": "builtins",
   "name": "dict.plot_x_t"
  }
 ],
 "results.raster_plot": [
  {
   "is_class": false,
   "is_explicit": false,
   "module": "nrv.nmod.results._unmyelinated_results",
   "module_short": "nrv.nmod.results",
   "name": "unmyelinated_results.raster_plot"
  },
  {
   "is_class": false,
   "is_explicit": false,
   "module": "nrv.nmod.results",
   "module_short": "nrv.nmod.results",
   "name": "unmyelinated_results.raster_plot"
  },
  {
   "is_class": false,
   "is_explicit": false,
   "module": "nrv.nmod",
   "module_short": "nrv.nmod",
   "name": "unmyelinated_results.raster_plot"
  },
  {
   "is_class": false,
   "is_explicit": false,
   "module": "nrv",
   "module_short": "nrv",
   "name": "unmyelinated_results.raster_plot"
  },
  {
   "is_class": false,
   "is_explicit": false,
   "module": "nrv.nmod.results._axons_results",
   "module_short": "nrv.nmod.results",
   "name": "axon_results.raster_plot"
  },
  {
   "is_class": false,
   "is_explicit": false,
   "module": "nrv.nmod.results",
   "module_short": "nrv.nmod.results",
   "name": "axon_results.raster_plot"
  },
  {
   "is_class": false,
   "is_explicit": false,
   "module": "nrv.nmod",
   "module_short": "nrv.nmod",
   "name": "axon_results.raster_plot"
  },
  {
   "is_class": false,
   "is_explicit": false,
   "module": "nrv",
   "module_short": "nrv",
   "name": "axon_results.raster_plot"
  },
  {
   "is_class": false,
   "is_explicit": false,
   "module": "nrv.backend._NRV_Results",
   "module_short": "nrv.backend._NRV_Results",
   "name": "sim_results.raster_plot"
  },
  {
   "is_class": false,
   "is_explicit": false,
   "module": "nrv.backend",
   "module_short": "nrv.backend",
   "name": "sim_results.raster_plot"
  },
  {
   "is_class": false,
   "is_explicit": false,
   "module": "nrv",
   "module_short": "nrv",
   "name": "sim_results.raster_plot"
  },
  {
   "is_class": false,
   "is_explicit": false,
   "module": "nrv.backend._NRV_Results",
   "module_short": "nrv.backend._NRV_Results",
   "name": "NRV_results.raster_plot"
  },
  {
   "is_class": false,
   "is_explicit": false,
   "module": "nrv.backend",
   "module_short": "nrv.backend",
   "name": "NRV_results.raster_plot"
  },
  {
   "is_class": false,
   "is_explicit": false,
   "module": "nrv",
   "module_short": "nrv",
   "name": "NRV_results.raster_plot"
  },
  {
   "is_class": false,
   "is_explicit": false,
   "module": "nrv.backend._NRV_Class",
   "module_short": "nrv.backend._NRV_Class",
   "name": "NRV_class.raster_plot"
  },
  {
   "is_class": false,
   "is_explicit": false,
   "module": "nrv.backend",
   "module_short": "nrv.backend",
   "name": "NRV_class.raster_plot"
  },
  {
   "is_class": false,
   "is_explicit": false,
   "module": "nrv",
   "module_short": "nrv",
   "name": "NRV_class.raster_plot"
  },
  {
   "is_class": false,
   "is_explicit": false,
   "module": "builtins",
   "module_short": "builtins",
   "name": "dict.raster_plot"
  }
 ],
 "results.rasterize": [
  {
   "is_class": false,
   "is_explicit": false,
   "module": "nrv.nmod.results._unmyelinated_results",
   "module_short": "nrv.nmod.results",
   "name": "unmyelinated_results.rasterize"
  },
  {
   "is_class": false,
   "is_explicit": false,
   "module": "nrv.nmod.results",
   "module_short": "nrv.nmod.results",
   "name": "unmyelinated_results.rasterize"
  },
  {
   "is_class": false,
   "is_explicit": false,
   "module": "nrv.nmod",
   "module_short": "nrv.nmod",
   "name": "unmyelinated_results.rasterize"
  },
  {
   "is_class": false,
   "is_explicit": false,
   "module": "nrv",
   "module_short": "nrv",
   "name": "unmyelinated_results.rasterize"
  },
  {
   "is_class": false,
   "is_explicit": false,
   "module": "nrv.nmod.results._axons_results",
   "module_short": "nrv.nmod.results",
   "name": "axon_results.rasterize"
  },
  {
   "is_class": false,
   "is_explicit": false,
   "module": "nrv.nmod.results",
   "module_short": "nrv.nmod.results",
   "name": "axon_results.rasterize"
  },
  {
   "is_class": false,
   "is_explicit": false,
   "module": "nrv.nmod",
   "module_short": "nrv.nmod",
   "name": "axon_results.rasterize"
  },
  {
   "is_class": false,
   "is_explicit": false,
   "module": "nrv",
   "module_short": "nrv",
   "name": "axon_results.rasterize"
  },
  {
   "is_class": false,
   "is_explicit": false,
   "module": "nrv.backend._NRV_Results",
   "module_short": "nrv.backend._NRV_Results",
   "name": "sim_results.rasterize"
  },
  {
   "is_class": false,
   "is_explicit": false,
   "module": "nrv.backend",
   "module_short": "nrv.backend",
   "name": "sim_results.rasterize"
  },
  {
   "is_class": false,
   "is_explicit": false,
   "module": "nrv",
   "module_short": "nrv",
   "name": "sim_results.rasterize"
  },
  {
   "is_class": false,
   "is_explicit": false,
   "module": "nrv.backend._NRV_Results",
   "module_short": "nrv.backend._NRV_Results",
   "name": "NRV_results.rasterize"
  },
  {
   "is_class": false,
   "is_explicit": false,
   "module": "nrv.backend",
   "module_short": "nrv.backend",
   "name": "NRV_results.rasterize"
  },
  {
   "is_class": false,
   "is_explicit": false,
   "module": "nrv",
   "module_short": "nrv",
   "name": "NRV_results.rasterize"
  },
  {
   "is_class": false,
   "is_explicit": false,
   "module": "nrv.backend._NRV_Class",
   "module_short": "nrv.backend._NRV_Class",
   "name": "NRV_class.rasterize"
  },
  {
   "is_class": false,
   "is_explicit": false,
   "module": "nrv.backend",
   "module_short": "nrv.backend",
   "name": "NRV_class.rasterize"
  },
  {
   "is_class": false,
   "is_explicit": false,
   "module": "nrv",
   "module_short": "nrv",
   "name": "NRV_class.rasterize"
  },
  {
   "is_class": false,
   "is_explicit": false,
   "module": "builtins",
   "module_short": "builtins",
   "name": "dict.rasterize"
  }
 ],
 "results.tstop": [
  {
   "is_class": false,
   "is_explicit": false,
   "module": "builtins",
   "module_short": "builtins",
   "name": "int"
  }
 ],
 "results.x_rec": [
  {
   "is_class": false,
   "is_explicit": false,
   "module": "numpy",
   "module_short": "numpy",
   "name": "ndarray"
  }
 ],
 "results_m": [
  {
   "is_class": false,
   "is_explicit": false,
   "module": "nrv.nmod.results._myelinated_results",
   "module_short": "nrv.nmod.results",
   "name": "myelinated_results"
  },
  {
   "is_class": false,
   "is_explicit": false,
   "module": "nrv.nmod.results",
   "module_short": "nrv.nmod.results",
   "name": "myelinated_results"
  },
  {
   "is_class": false,
   "is_explicit": false,
   "module": "nrv.nmod",
   "module_short": "nrv.nmod",
   "name": "myelinated_results"
  },
  {
   "is_class": false,
   "is_explicit": false,
   "module": "nrv",
   "module_short": "nrv",
   "name": "myelinated_results"
  }
 ],
 "results_m.colormap_plot": [
  {
   "is_class": false,
   "is_explicit": false,
   "module": "nrv.nmod.results._myelinated_results",
   "module_short": "nrv.nmod.results",
   "name": "myelinated_results.colormap_plot"
  },
  {
   "is_class": false,
   "is_explicit": false,
   "module": "nrv.nmod.results",
   "module_short": "nrv.nmod.results",
   "name": "myelinated_results.colormap_plot"
  },
  {
   "is_class": false,
   "is_explicit": false,
   "module": "nrv.nmod",
   "module_short": "nrv.nmod",
   "name": "myelinated_results.colormap_plot"
  },
  {
   "is_class": false,
   "is_explicit": false,
   "module": "nrv",
   "module_short": "nrv",
   "name": "myelinated_results.colormap_plot"
  },
  {
   "is_class": false,
   "is_explicit": false,
   "module": "nrv.nmod.results._axons_results",
   "module_short": "nrv.nmod.results",
   "name": "axon_results.colormap_plot"
  },
  {
   "is_class": false,
   "is_explicit": false,
   "module": "nrv.nmod.results",
   "module_short": "nrv.nmod.results",
   "name": "axon_results.colormap_plot"
  },
  {
   "is_class": false,
   "is_explicit": false,
   "module": "nrv.nmod",
   "module_short": "nrv.nmod",
   "name": "axon_results.colormap_plot"
  },
  {
   "is_class": false,
   "is_explicit": false,
   "module": "nrv",
   "module_short": "nrv",
   "name": "axon_results.colormap_plot"
  },
  {
   "is_class": false,
   "is_explicit": false,
   "module": "nrv.backend._NRV_Results",
   "module_short": "nrv.backend._NRV_Results",
   "name": "sim_results.colormap_plot"
  },
  {
   "is_class": false,
   "is_explicit": false,
   "module": "nrv.backend",
   "module_short": "nrv.backend",
   "name": "sim_results.colormap_plot"
  },
  {
   "is_class": false,
   "is_explicit": false,
   "module": "nrv",
   "module_short": "nrv",
   "name": "sim_results.colormap_plot"
  },
  {
   "is_class": false,
   "is_explicit": false,
   "module": "nrv.backend._NRV_Results",
   "module_short": "nrv.backend._NRV_Results",
   "name": "NRV_results.colormap_plot"
  },
  {
   "is_class": false,
   "is_explicit": false,
   "module": "nrv.backend",
   "module_short": "nrv.backend",
   "name": "NRV_results.colormap_plot"
  },
  {
   "is_class": false,
   "is_explicit": false,
   "module": "nrv",
   "module_short": "nrv",
   "name": "NRV_results.colormap_plot"
  },
  {
   "is_class": false,
   "is_explicit": false,
   "module": "nrv.backend._NRV_Class",
   "module_short": "nrv.backend._NRV_Class",
   "name": "NRV_class.colormap_plot"
  },
  {
   "is_class": false,
   "is_explicit": false,
   "module": "nrv.backend",
   "module_short": "nrv.backend",
   "name": "NRV_class.colormap_plot"
  },
  {
   "is_class": false,
   "is_explicit": false,
   "module": "nrv",
   "module_short": "nrv",
   "name": "NRV_class.colormap_plot"
  },
  {
   "is_class": false,
   "is_explicit": false,
   "module": "builtins",
   "module_short": "builtins",
   "name": "dict.colormap_plot"
  }
 ],
 "results_m.plot_x_t": [
  {
   "is_class": false,
   "is_explicit": false,
   "module": "nrv.nmod.results._myelinated_results",
   "module_short": "nrv.nmod.results",
   "name": "myelinated_results.plot_x_t"
  },
  {
   "is_class": false,
   "is_explicit": false,
   "module": "nrv.nmod.results",
   "module_short": "nrv.nmod.results",
   "name": "myelinated_results.plot_x_t"
  },
  {
   "is_class": false,
   "is_explicit": false,
   "module": "nrv.nmod",
   "module_short": "nrv.nmod",
   "name": "myelinated_results.plot_x_t"
  },
  {
   "is_class": false,
   "is_explicit": false,
   "module": "nrv",
   "module_short": "nrv",
   "name": "myelinated_results.plot_x_t"
  },
  {
   "is_class": false,
   "is_explicit": false,
   "module": "nrv.nmod.results._axons_results",
   "module_short": "nrv.nmod.results",
   "name": "axon_results.plot_x_t"
  },
  {
   "is_class": false,
   "is_explicit": false,
   "module": "nrv.nmod.results",
   "module_short": "nrv.nmod.results",
   "name": "axon_results.plot_x_t"
  },
  {
   "is_class": false,
   "is_explicit": false,
   "module": "nrv.nmod",
   "module_short": "nrv.nmod",
   "name": "axon_results.plot_x_t"
  },
  {
   "is_class": false,
   "is_explicit": false,
   "module": "nrv",
   "module_short": "nrv",
   "name": "axon_results.plot_x_t"
  },
  {
   "is_class": false,
   "is_explicit": false,
   "module": "nrv.backend._NRV_Results",
   "module_short": "nrv.backend._NRV_Results",
   "name": "sim_results.plot_x_t"
  },
  {
   "is_class": false,
   "is_explicit": false,
   "module": "nrv.backend",
   "module_short": "nrv.backend",
   "name": "sim_results.plot_x_t"
  },
  {
   "is_class": false,
   "is_explicit": false,
   "module": "nrv",
   "module_short": "nrv",
   "name": "sim_results.plot_x_t"
  },
  {
   "is_class": false,
   "is_explicit": false,
   "module": "nrv.backend._NRV_Results",
   "module_short": "nrv.backend._NRV_Results",
   "name": "NRV_results.plot_x_t"
  },
  {
   "is_class": false,
   "is_explicit": false,
   "module": "nrv.backend",
   "module_short": "nrv.backend",
   "name": "NRV_results.plot_x_t"
  },
  {
   "is_class": false,
   "is_explicit": false,
   "module": "nrv",
   "module_short": "nrv",
   "name": "NRV_results.plot_x_t"
  },
  {
   "is_class": false,
   "is_explicit": false,
   "module": "nrv.backend._NRV_Class",
   "module_short": "nrv.backend._NRV_Class",
   "name": "NRV_class.plot_x_t"
  },
  {
   "is_class": false,
   "is_explicit": false,
   "module": "nrv.backend",
   "module_short": "nrv.backend",
   "name": "NRV_class.plot_x_t"
  },
  {
   "is_class": false,
   "is_explicit": false,
   "module": "nrv",
   "module_short": "nrv",
   "name": "NRV_class.plot_x_t"
  },
  {
   "is_class": false,
   "is_explicit": false,
   "module": "builtins",
   "module_short": "builtins",
   "name": "dict.plot_x_t"
  }
 ],
 "results_m.raster_plot": [
  {
   "is_class": false,
   "is_explicit": false,
   "module": "nrv.nmod.results._myelinated_results",
   "module_short": "nrv.nmod.results",
   "name": "myelinated_results.raster_plot"
  },
  {
   "is_class": false,
   "is_explicit": false,
   "module": "nrv.nmod.results",
   "module_short": "nrv.nmod.results",
   "name": "myelinated_results.raster_plot"
  },
  {
   "is_class": false,
   "is_explicit": false,
   "module": "nrv.nmod",
   "module_short": "nrv.nmod",
   "name": "myelinated_results.raster_plot"
  },
  {
   "is_class": false,
   "is_explicit": false,
   "module": "nrv",
   "module_short": "nrv",
   "name": "myelinated_results.raster_plot"
  },
  {
   "is_class": false,
   "is_explicit": false,
   "module": "nrv.nmod.results._axons_results",
   "module_short": "nrv.nmod.results",
   "name": "axon_results.raster_plot"
  },
  {
   "is_class": false,
   "is_explicit": false,
   "module": "nrv.nmod.results",
   "module_short": "nrv.nmod.results",
   "name": "axon_results.raster_plot"
  },
  {
   "is_class": false,
   "is_explicit": false,
   "module": "nrv.nmod",
   "module_short": "nrv.nmod",
   "name": "axon_results.raster_plot"
  },
  {
   "is_class": false,
   "is_explicit": false,
   "module": "nrv",
   "module_short": "nrv",
   "name": "axon_results.raster_plot"
  },
  {
   "is_class": false,
   "is_explicit": false,
   "module": "nrv.backend._NRV_Results",
   "module_short": "nrv.backend._NRV_Results",
   "name": "sim_results.raster_plot"
  },
  {
   "is_class": false,
   "is_explicit": false,
   "module": "nrv.backend",
   "module_short": "nrv.backend",
   "name": "sim_results.raster_plot"
  },
  {
   "is_class": false,
   "is_explicit": false,
   "module": "nrv",
   "module_short": "nrv",
   "name": "sim_results.raster_plot"
  },
  {
   "is_class": false,
   "is_explicit": false,
   "module": "nrv.backend._NRV_Results",
   "module_short": "nrv.backend._NRV_Results",
   "name": "NRV_results.raster_plot"
  },
  {
   "is_class": false,
   "is_explicit": false,
   "module": "nrv.backend",
   "module_short": "nrv.backend",
   "name": "NRV_results.raster_plot"
  },
  {
   "is_class": false,
   "is_explicit": false,
   "module": "nrv",
   "module_short": "nrv",
   "name": "NRV_results.raster_plot"
  },
  {
   "is_class": false,
   "is_explicit": false,
   "module": "nrv.backend._NRV_Class",
   "module_short": "nrv.backend._NRV_Class",
   "name": "NRV_class.raster_plot"
  },
  {
   "is_class": false,
   "is_explicit": false,
   "module": "nrv.backend",
   "module_short": "nrv.backend",
   "name": "NRV_class.raster_plot"
  },
  {
   "is_class": false,
   "is_explicit": false,
   "module": "nrv",
   "module_short": "nrv",
   "name": "NRV_class.raster_plot"
  },
  {
   "is_class": false,
   "is_explicit": false,
   "module": "builtins",
   "module_short": "builtins",
   "name": "dict.raster_plot"
  }
 ],
 "results_m.rasterize": [
  {
   "is_class": false,
   "is_explicit": false,
   "module": "nrv.nmod.results._myelinated_results",
   "module_short": "nrv.nmod.results",
   "name": "myelinated_results.rasterize"
  },
  {
   "is_class": false,
   "is_explicit": false,
   "module": "nrv.nmod.results",
   "module_short": "nrv.nmod.results",
   "name": "myelinated_results.rasterize"
  },
  {
   "is_class": false,
   "is_explicit": false,
   "module": "nrv.nmod",
   "module_short": "nrv.nmod",
   "name": "myelinated_results.rasterize"
  },
  {
   "is_class": false,
   "is_explicit": false,
   "module": "nrv",
   "module_short": "nrv",
   "name": "myelinated_results.rasterize"
  },
  {
   "is_class": false,
   "is_explicit": false,
   "module": "nrv.nmod.results._axons_results",
   "module_short": "nrv.nmod.results",
   "name": "axon_results.rasterize"
  },
  {
   "is_class": false,
   "is_explicit": false,
   "module": "nrv.nmod.results",
   "module_short": "nrv.nmod.results",
   "name": "axon_results.rasterize"
  },
  {
   "is_class": false,
   "is_explicit": false,
   "module": "nrv.nmod",
   "module_short": "nrv.nmod",
   "name": "axon_results.rasterize"
  },
  {
   "is_class": false,
   "is_explicit": false,
   "module": "nrv",
   "module_short": "nrv",
   "name": "axon_results.rasterize"
  },
  {
   "is_class": false,
   "is_explicit": false,
   "module": "nrv.backend._NRV_Results",
   "module_short": "nrv.backend._NRV_Results",
   "name": "sim_results.rasterize"
  },
  {
   "is_class": false,
   "is_explicit": false,
   "module": "nrv.backend",
   "module_short": "nrv.backend",
   "name": "sim_results.rasterize"
  },
  {
   "is_class": false,
   "is_explicit": false,
   "module": "nrv",
   "module_short": "nrv",
   "name": "sim_results.rasterize"
  },
  {
   "is_class": false,
   "is_explicit": false,
   "module": "nrv.backend._NRV_Results",
   "module_short": "nrv.backend._NRV_Results",
   "name": "NRV_results.rasterize"
  },
  {
   "is_class": false,
   "is_explicit": false,
   "module": "nrv.backend",
   "module_short": "nrv.backend",
   "name": "NRV_results.rasterize"
  },
  {
   "is_class": false,
   "is_explicit": false,
   "module": "nrv",
   "module_short": "nrv",
   "name": "NRV_results.rasterize"
  },
  {
   "is_class": false,
   "is_explicit": false,
   "module": "nrv.backend._NRV_Class",
   "module_short": "nrv.backend._NRV_Class",
   "name": "NRV_class.rasterize"
  },
  {
   "is_class": false,
   "is_explicit": false,
   "module": "nrv.backend",
   "module_short": "nrv.backend",
   "name": "NRV_class.rasterize"
  },
  {
   "is_class": false,
   "is_explicit": false,
   "module": "nrv",
   "module_short": "nrv",
   "name": "NRV_class.rasterize"
  },
  {
   "is_class": false,
   "is_explicit": false,
   "module": "builtins",
   "module_short": "builtins",
   "name": "dict.rasterize"
  }
 ],
 "results_m.tstop": [
  {
   "is_class": false,
   "is_explicit": false,
   "module": "builtins",
   "module_short": "builtins",
   "name": "int"
  }
 ],
 "results_m.x_rec": [
  {
   "is_class": false,
   "is_explicit": false,
   "module": "numpy",
   "module_short": "numpy",
   "name": "ndarray"
  }
 ],
 "t_sim": [
  {
   "is_class": false,
   "is_explicit": false,
   "module": "builtins",
   "module_short": "builtins",
   "name": "int"
  }
 ],
 "t_start": [
  {
   "is_class": false,
   "is_explicit": false,
   "module": "builtins",
   "module_short": "builtins",
   "name": "int"
  }
 ],
 "vmem": [
  {
   "is_class": false,
   "is_explicit": false,
   "module": "numpy",
   "module_short": "numpy",
   "name": "ndarray"
  }
 ],
 "vmem_attribute": [
  {
   "is_class": false,
   "is_explicit": false,
   "module": "numpy",
   "module_short": "numpy",
   "name": "ndarray"
  }
 ],
 "x_idx_mid": [
  {
   "is_class": false,
   "is_explicit": false,
   "module": "builtins",
   "module_short": "builtins",
   "name": "int"
  }
 ],
 "x_start": [
  {
   "is_class": false,
   "is_explicit": false,
   "module": "builtins",
   "module_short": "builtins",
   "name": "int"
  }
 ],
 "y": [
  {
   "is_class": false,
   "is_explicit": false,
   "module": "builtins",
   "module_short": "builtins",
   "name": "int"
  }
 ],
 "z": [
  {
   "is_class": false,
   "is_explicit": false,
   "module": "builtins",
   "module_short": "builtins",
   "name": "int"
  }
 ]
}