{
 "E1": [
  {
   "is_class": false,
   "is_explicit": false,
   "module": "nrv.fmod._electrodes",
   "module_short": "nrv",
   "name": "point_source_electrode"
  },
  {
   "is_class": false,
   "is_explicit": false,
   "module": "nrv.fmod",
   "module_short": "nrv",
   "name": "point_source_electrode"
  },
  {
   "is_class": false,
   "is_explicit": false,
   "module": "nrv",
   "module_short": "nrv",
   "name": "point_source_electrode"
  }
 ],
 "L": [
  {
   "is_class": false,
   "is_explicit": false,
   "module": "builtins",
   "module_short": "builtins",
   "name": "int"
  }
 ],
 "__name__": [
  {
   "is_class": false,
   "is_explicit": false,
   "module": "builtins",
   "module_short": "builtins",
   "name": "str"
  }
 ],
 "ax": [
  {
   "is_class": false,
   "is_explicit": false,
   "module": "matplotlib.axes._axes",
   "module_short": "matplotlib.axes",
   "name": "Axes"
  },
  {
   "is_class": false,
   "is_explicit": false,
   "module": "matplotlib.axes",
   "module_short": "matplotlib.axes",
   "name": "Axes"
  },
  {
   "is_class": false,
   "is_explicit": false,
   "module": "matplotlib",
   "module_short": "matplotlib",
   "name": "Axes"
  }
 ],
 "ax.set_title": [
  {
   "is_class": false,
   "is_explicit": false,
   "module": "matplotlib.axes._axes",
   "module_short": "matplotlib.axes",
   "name": "Axes.set_title"
  },
  {
   "is_class": false,
   "is_explicit": false,
   "module": "matplotlib.axes",
   "module_short": "matplotlib.axes",
   "name": "Axes.set_title"
  },
  {
   "is_class": false,
   "is_explicit": false,
   "module": "matplotlib",
   "module_short": "matplotlib",
   "name": "Axes.set_title"
  },
  {
   "is_class": false,
   "is_explicit": false,
   "module": "matplotlib.axes._base",
   "module_short": "matplotlib.axes._base",
   "name": "_AxesBase.set_title"
  },
  {
   "is_class": false,
   "is_explicit": false,
   "module": "matplotlib.axes",
   "module_short": "matplotlib.axes",
   "name": "_AxesBase.set_title"
  },
  {
   "is_class": false,
   "is_explicit": false,
   "module": "matplotlib",
   "module_short": "matplotlib",
   "name": "_AxesBase.set_title"
  },
  {
   "is_class": false,
   "is_explicit": false,
   "module": "matplotlib.artist",
   "module_short": "matplotlib.artist",
   "name": "Artist.set_title"
  },
  {
   "is_class": false,
   "is_explicit": false,
   "module": "matplotlib",
   "module_short": "matplotlib",
   "name": "Artist.set_title"
  }
 ],
 "ax.set_xlabel": [
  {
   "is_class": false,
   "is_explicit": false,
   "module": "matplotlib.axes._axes",
   "module_short": "matplotlib.axes",
   "name": "Axes.set_xlabel"
  },
  {
   "is_class": false,
   "is_explicit": false,
   "module": "matplotlib.axes",
   "module_short": "matplotlib.axes",
   "name": "Axes.set_xlabel"
  },
  {
   "is_class": false,
   "is_explicit": false,
   "module": "matplotlib",
   "module_short": "matplotlib",
   "name": "Axes.set_xlabel"
  },
  {
   "is_class": false,
   "is_explicit": false,
   "module": "matplotlib.axes._base",
   "module_short": "matplotlib.axes._base",
   "name": "_AxesBase.set_xlabel"
  },
  {
   "is_class": false,
   "is_explicit": false,
   "module": "matplotlib.axes",
   "module_short": "matplotlib.axes",
   "name": "_AxesBase.set_xlabel"
  },
  {
   "is_class": false,
   "is_explicit": false,
   "module": "matplotlib",
   "module_short": "matplotlib",
   "name": "_AxesBase.set_xlabel"
  },
  {
   "is_class": false,
   "is_explicit": false,
   "module": "matplotlib.artist",
   "module_short": "matplotlib.artist",
   "name": "Artist.set_xlabel"
  },
  {
   "is_class": false,
   "is_explicit": false,
   "module": "matplotlib",
   "module_short": "matplotlib",
   "name": "Artist.set_xlabel"
  }
 ],
 "ax.set_ylabel": [
  {
   "is_class": false,
   "is_explicit": false,
   "module": "matplotlib.axes._axes",
   "module_short": "matplotlib.axes",
   "name": "Axes.set_ylabel"
  },
  {
   "is_class": false,
   "is_explicit": false,
   "module": "matplotlib.axes",
   "module_short": "matplotlib.axes",
   "name": "Axes.set_ylabel"
  },
  {
   "is_class": false,
   "is_explicit": false,
   "module": "matplotlib",
   "module_short": "matplotlib",
   "name": "Axes.set_ylabel"
  },
  {
   "is_class": false,
   "is_explicit": false,
   "module": "matplotlib.axes._base",
   "module_short": "matplotlib.axes._base",
   "name": "_AxesBase.set_ylabel"
  },
  {
   "is_class": false,
   "is_explicit": false,
   "module": "matplotlib.axes",
   "module_short": "matplotlib.axes",
   "name": "_AxesBase.set_ylabel"
  },
  {
   "is_class": false,
   "is_explicit": false,
   "module": "matplotlib",
   "module_short": "matplotlib",
   "name": "_AxesBase.set_ylabel"
  },
  {
   "is_class": false,
   "is_explicit": false,
   "module": "matplotlib.artist",
   "module_short": "matplotlib.artist",
   "name": "Artist.set_ylabel"
  },
  {
   "is_class": false,
   "is_explicit": false,
   "module": "matplotlib",
   "module_short": "matplotlib",
   "name": "Artist.set_ylabel"
  }
 ],
 "axon1": [
  {
   "is_class": false,
   "is_explicit": false,
   "module": "nrv.nmod._unmyelinated",
   "module_short": "nrv",
   "name": "unmyelinated"
  },
  {
   "is_class": false,
   "is_explicit": false,
   "module": "nrv.nmod",
   "module_short": "nrv",
   "name": "unmyelinated"
  },
  {
   "is_class": false,
   "is_explicit": false,
   "module": "nrv",
   "module_short": "nrv",
   "name": "unmyelinated"
  }
 ],
 "axon1.attach_extracellular_stimulation": [
  {
   "is_class": false,
   "is_explicit": false,
   "module": "nrv.nmod._unmyelinated",
   "module_short": "nrv",
   "name": "unmyelinated.attach_extracellular_stimulation"
  },
  {
   "is_class": false,
   "is_explicit": false,
   "module": "nrv.nmod",
   "module_short": "nrv",
   "name": "unmyelinated.attach_extracellular_stimulation"
  },
  {
   "is_class": false,
   "is_explicit": false,
   "module": "nrv",
   "module_short": "nrv",
   "name": "unmyelinated.attach_extracellular_stimulation"
  },
  {
   "is_class": false,
   "is_explicit": false,
   "module": "nrv.nmod._axons",
   "module_short": "nrv",
   "name": "axon.attach_extracellular_stimulation"
  },
  {
   "is_class": false,
   "is_explicit": false,
   "module": "nrv.nmod",
   "module_short": "nrv",
   "name": "axon.attach_extracellular_stimulation"
  },
  {
   "is_class": false,
   "is_explicit": false,
   "module": "nrv",
   "module_short": "nrv",
   "name": "axon.attach_extracellular_stimulation"
  },
  {
   "is_class": false,
   "is_explicit": false,
   "module": "nrv.backend._NRV_Simulable",
   "module_short": "nrv.backend._NRV_Simulable",
   "name": "NRV_simulable.attach_extracellular_stimulation"
  },
  {
   "is_class": false,
   "is_explicit": false,
   "module": "nrv.backend",
   "module_short": "nrv.backend",
   "name": "NRV_simulable.attach_extracellular_stimulation"
  },
  {
   "is_class": false,
   "is_explicit": false,
   "module": "nrv",
   "module_short": "nrv",
   "name": "NRV_simulable.attach_extracellular_stimulation"
  },
  {
   "is_class": false,
   "is_explicit": false,
   "module": "nrv.backend._NRV_Class",
   "module_short": "nrv.backend._NRV_Class",
   "name": "NRV_class.attach_extracellular_stimulation"
  },
  {
   "is_class": false,
   "is_explicit": false,
   "module": "nrv.backend",
   "module_short": "nrv.backend",
   "name": "NRV_class.attach_extracellular_stimulation"
  },
  {
   "is_class": false,
   "is_explicit": false,
   "module": "nrv",
   "module_short": "nrv",
   "name": "NRV_class.attach_extracellular_stimulation"
  }
 ],
 "axon1.insert_I_Clamp": [
  {
   "is_class": false,
   "is_explicit": false,
   "module": "nrv.nmod._unmyelinated",
   "module_short": "nrv",
   "name": "unmyelinated.insert_I_Clamp"
  },
  {
   "is_class": false,
   "is_explicit": false,
   "module": "nrv.nmod",
   "module_short": "nrv",
   "name": "unmyelinated.insert_I_Clamp"
  },
  {
   "is_class": false,
   "is_explicit": false,
   "module": "nrv",
   "module_short": "nrv",
   "name": "unmyelinated.insert_I_Clamp"
  },
  {
   "is_class": false,
   "is_explicit": false,
   "module": "nrv.nmod._axons",
   "module_short": "nrv",
   "name": "axon.insert_I_Clamp"
  },
  {
   "is_class": false,
   "is_explicit": false,
   "module": "nrv.nmod",
   "module_short": "nrv",
   "name": "axon.insert_I_Clamp"
  },
  {
   "is_class": false,
   "is_explicit": false,
   "module": "nrv",
   "module_short": "nrv",
   "name": "axon.insert_I_Clamp"
  },
  {
   "is_class": false,
   "is_explicit": false,
   "module": "nrv.backend._NRV_Simulable",
   "module_short": "nrv.backend._NRV_Simulable",
   "name": "NRV_simulable.insert_I_Clamp"
  },
  {
   "is_class": false,
   "is_explicit": false,
   "module": "nrv.backend",
   "module_short": "nrv.backend",
   "name": "NRV_simulable.insert_I_Clamp"
  },
  {
   "is_class": false,
   "is_explicit": false,
   "module": "nrv",
   "module_short": "nrv",
   "name": "NRV_simulable.insert_I_Clamp"
  },
  {
   "is_class": false,
   "is_explicit": false,
   "module": "nrv.backend._NRV_Class",
   "module_short": "nrv.backend._NRV_Class",
   "name": "NRV_class.insert_I_Clamp"
  },
  {
   "is_class": false,
   "is_explicit": false,
   "module": "nrv.backend",
   "module_short": "nrv.backend",
   "name": "NRV_class.insert_I_Clamp"
  },
  {
   "is_class": false,
   "is_explicit": false,
   "module": "nrv",
   "module_short": "nrv",
   "name": "NRV_class.insert_I_Clamp"
  }
 ],
 "axon1.simulate": [
  {
   "is_class": false,
   "is_explicit": false,
   "module": "nrv.nmod._unmyelinated",
   "module_short": "nrv",
   "name": "unmyelinated.simulate"
  },
  {
   "is_class": false,
   "is_explicit": false,
   "module": "nrv.nmod",
   "module_short": "nrv",
   "name": "unmyelinated.simulate"
  },
  {
   "is_class": false,
   "is_explicit": false,
   "module": "nrv",
   "module_short": "nrv",
   "name": "unmyelinated.simulate"
  },
  {
   "is_class": false,
   "is_explicit": false,
   "module": "nrv.nmod._axons",
   "module_short": "nrv",
   "name": "axon.simulate"
  },
  {
   "is_class": false,
   "is_explicit": false,
   "module": "nrv.nmod",
   "module_short": "nrv",
   "name": "axon.simulate"
  },
  {
   "is_class": false,
   "is_explicit": false,
   "module": "nrv",
   "module_short": "nrv",
   "name": "axon.simulate"
  },
  {
   "is_class": false,
   "is_explicit": false,
   "module": "nrv.backend._NRV_Simulable",
   "module_short": "nrv",
   "name": "NRV_simulable.simulate"
  },
  {
   "is_class": false,
   "is_explicit": false,
   "module": "nrv.backend",
   "module_short": "nrv",
   "name": "NRV_simulable.simulate"
  },
  {
   "is_class": false,
   "is_explicit": false,
   "module": "nrv",
   "module_short": "nrv",
   "name": "NRV_simulable.simulate"
  },
  {
   "is_class": false,
   "is_explicit": false,
   "module": "nrv.backend._NRV_Class",
   "module_short": "nrv.backend._NRV_Class",
   "name": "NRV_class.simulate"
  },
  {
   "is_class": false,
   "is_explicit": false,
   "module": "nrv.backend",
   "module_short": "nrv.backend",
   "name": "NRV_class.simulate"
  },
  {
   "is_class": false,
   "is_explicit": false,
   "module": "nrv",
   "module_short": "nrv",
   "name": "NRV_class.simulate"
  }
 ],
 "axs": [
  {
   "is_class": false,
   "is_explicit": false,
   "module": "numpy",
   "module_short": "numpy",
   "name": "ndarray"
  }
 ],
 "b_duration": [
  {
   "is_class": false,
   "is_explicit": false,
   "module": "builtins",
   "module_short": "builtins",
   "name": "int"
  }
 ],
 "b_start": [
  {
   "is_class": false,
   "is_explicit": false,
   "module": "builtins",
   "module_short": "builtins",
   "name": "int"
  }
 ],
 "block_amp": [
  {
   "is_class": false,
   "is_explicit": false,
   "module": "builtins",
   "module_short": "builtins",
   "name": "int"
  }
 ],
 "block_freq": [
  {
   "is_class": false,
   "is_explicit": false,
   "module": "builtins",
   "module_short": "builtins",
   "name": "int"
  }
 ],
 "cbar": [
  {
   "is_class": false,
   "is_explicit": false,
   "module": "matplotlib.colorbar",
   "module_short": "matplotlib.colorbar",
   "name": "Colorbar"
  },
  {
   "is_class": false,
   "is_explicit": false,
   "module": "matplotlib",
   "module_short": "matplotlib",
   "name": "Colorbar"
  }
 ],
 "cbar.set_label": [
  {
   "is_class": false,
   "is_explicit": false,
   "module": "matplotlib.colorbar",
   "module_short": "matplotlib.colorbar",
   "name": "Colorbar.set_label"
  },
  {
   "is_class": false,
   "is_explicit": false,
   "module": "matplotlib",
   "module_short": "matplotlib",
   "name": "Colorbar.set_label"
  }
 ],
 "diam": [
  {
   "is_class": false,
   "is_explicit": false,
   "module": "builtins",
   "module_short": "builtins",
   "name": "int"
  }
 ],
 "dt": [
  {
   "is_class": false,
   "is_explicit": false,
   "module": "builtins",
   "module_short": "builtins",
   "name": "float"
  }
 ],
 "fig": [
  {
   "is_class": false,
   "is_explicit": false,
   "module": "matplotlib.figure",
   "module_short": "matplotlib.figure",
   "name": "Figure"
  },
  {
   "is_class": false,
   "is_explicit": false,
   "module": "matplotlib",
   "module_short": "matplotlib",
   "name": "Figure"
  }
 ],
 "material": [
  {
   "is_class": false,
   "is_explicit": false,
   "module": "nrv.fmod._materials",
   "module_short": "nrv",
   "name": "material"
  },
  {
   "is_class": false,
   "is_explicit": false,
   "module": "nrv.fmod",
   "module_short": "nrv",
   "name": "material"
  },
  {
   "is_class": false,
   "is_explicit": false,
   "module": "nrv",
   "module_short": "nrv",
   "name": "material"
  }
 ],
 "model": [
  {
   "is_class": false,
   "is_explicit": false,
   "module": "builtins",
   "module_short": "builtins",
   "name": "str"
  }
 ],
 "n_seg": [
  {
   "is_class": false,
   "is_explicit": false,
   "module": "numpy",
   "module_short": "numpy",
   "name": "int32"
  }
 ],
 "np.int32": [
  {
   "is_class": true,
   "is_explicit": false,
   "module": "numpy",
   "module_short": "numpy",
   "name": "int32"
  },
  {
   "is_class": true,
   "is_explicit": false,
   "module": "numpy",
   "module_short": "numpy",
   "name": "signedinteger"
  },
  {
   "is_class": true,
   "is_explicit": false,
   "module": "numpy",
   "module_short": "numpy",
   "name": "integer"
  },
  {
   "is_class": true,
   "is_explicit": false,
   "module": "numpy",
   "module_short": "numpy",
   "name": "number"
  },
  {
   "is_class": true,
   "is_explicit": false,
   "module": "numpy",
   "module_short": "numpy",
   "name": "generic"
  },
  {
   "is_class": false,
   "is_explicit": false,
   "module": "numpy",
   "module_short": "numpy",
   "name": "int32"
  }
 ],
 "np.max": [
  {
   "is_class": false,
   "is_explicit": false,
   "module": "numpy",
   "module_short": "numpy",
   "name": "_ArrayFunctionDispatcher"
  },
  {
   "is_class": false,
   "is_explicit": false,
   "module": "numpy",
   "module_short": "numpy",
   "name": "max"
  }
 ],
 "nrv.load_material": [
  {
   "is_class": false,
   "is_explicit": false,
   "module": "builtins",
   "module_short": "builtins",
   "name": "function"
  },
  {
   "is_class": false,
   "is_explicit": false,
   "module": "nrv",
   "module_short": "nrv",
   "name": "load_material"
  }
 ],
 "nrv.point_source_electrode": [
  {
   "is_class": true,
   "is_explicit": false,
   "module": "nrv.fmod._electrodes",
   "module_short": "nrv",
   "name": "point_source_electrode"
  },
  {
   "is_class": true,
   "is_explicit": false,
   "module": "nrv.fmod",
   "module_short": "nrv",
   "name": "point_source_electrode"
  },
  {
   "is_class": true,
   "is_explicit": false,
   "module": "nrv",
   "module_short": "nrv",
   "name": "point_source_electrode"
  },
  {
   "is_class": true,
   "is_explicit": false,
   "module": "nrv.fmod._electrodes",
   "module_short": "nrv",
   "name": "electrode"
  },
  {
   "is_class": true,
   "is_explicit": false,
   "module": "nrv.fmod",
   "module_short": "nrv",
   "name": "electrode"
  },
  {
   "is_class": true,
   "is_explicit": false,
   "module": "nrv",
   "module_short": "nrv",
   "name": "electrode"
  },
  {
   "is_class": true,
   "is_explicit": false,
   "module": "nrv.backend._NRV_Class",
   "module_short": "nrv",
   "name": "NRV_class"
  },
  {
   "is_class": true,
   "is_explicit": false,
   "module": "nrv.backend",
   "module_short": "nrv",
   "name": "NRV_class"
  },
  {
   "is_class": true,
   "is_explicit": false,
   "module": "nrv",
   "module_short": "nrv",
   "name": "NRV_class"
  },
  {
   "is_class": false,
   "is_explicit": false,
   "module": "nrv",
   "module_short": "nrv",
   "name": "point_source_electrode"
  }
 ],
 "nrv.stimulation": [
  {
   "is_class": true,
   "is_explicit": false,
   "module": "nrv.fmod._extracellular",
   "module_short": "nrv",
   "name": "stimulation"
  },
  {
   "is_class": true,
   "is_explicit": false,
   "module": "nrv.fmod",
   "module_short": "nrv",
   "name": "stimulation"
  },
  {
   "is_class": true,
   "is_explicit": false,
   "module": "nrv",
   "module_short": "nrv",
   "name": "stimulation"
  },
  {
   "is_class": true,
   "is_explicit": false,
   "module": "nrv.fmod._extracellular",
   "module_short": "nrv",
   "name": "extracellular_context"
  },
  {
   "is_class": true,
   "is_explicit": false,
   "module": "nrv.fmod",
   "module_short": "nrv",
   "name": "extracellular_context"
  },
  {
   "is_class": true,
   "is_explicit": false,
   "module": "nrv",
   "module_short": "nrv",
   "name": "extracellular_context"
  },
  {
   "is_class": true,
   "is_explicit": false,
   "module": "nrv.backend._NRV_Class",
   "module_short": "nrv",
   "name": "NRV_class"
  },
  {
   "is_class": true,
   "is_explicit": false,
   "module": "nrv.backend",
   "module_short": "nrv",
   "name": "NRV_class"
  },
  {
   "is_class": true,
   "is_explicit": false,
   "module": "nrv",
   "module_short": "nrv",
   "name": "NRV_class"
  },
  {
   "is_class": false,
   "is_explicit": false,
   "module": "nrv",
   "module_short": "nrv",
   "name": "stimulation"
  }
 ],
 "nrv.stimulus": [
  {
   "is_class": true,
   "is_explicit": false,
   "module": "nrv.utils._stimulus",
   "module_short": "nrv",
   "name": "stimulus"
  },
  {
   "is_class": true,
   "is_explicit": false,
   "module": "nrv.utils",
   "module_short": "nrv",
   "name": "stimulus"
  },
  {
   "is_class": true,
   "is_explicit": false,
   "module": "nrv",
   "module_short": "nrv",
   "name": "stimulus"
  },
  {
   "is_class": true,
   "is_explicit": false,
   "module": "nrv.backend._NRV_Class",
   "module_short": "nrv",
   "name": "NRV_class"
  },
  {
   "is_class": true,
   "is_explicit": false,
   "module": "nrv.backend",
   "module_short": "nrv",
   "name": "NRV_class"
  },
  {
   "is_class": true,
   "is_explicit": false,
   "module": "nrv",
   "module_short": "nrv",
   "name": "NRV_class"
  },
  {
   "is_class": false,
   "is_explicit": false,
   "module": "nrv",
   "module_short": "nrv",
   "name": "stimulus"
  }
 ],
 "nrv.unmyelinated": [
  {
   "is_class": true,
   "is_explicit": false,
   "module": "nrv.nmod._unmyelinated",
   "module_short": "nrv",
   "name": "unmyelinated"
  },
  {
   "is_class": true,
   "is_explicit": false,
   "module": "nrv.nmod",
   "module_short": "nrv",
   "name": "unmyelinated"
  },
  {
   "is_class": true,
   "is_explicit": false,
   "module": "nrv",
   "module_short": "nrv",
   "name": "unmyelinated"
  },
  {
   "is_class": true,
   "is_explicit": false,
   "module": "nrv.nmod._axons",
   "module_short": "nrv",
   "name": "axon"
  },
  {
   "is_class": true,
   "is_explicit": false,
   "module": "nrv.nmod",
   "module_short": "nrv",
   "name": "axon"
  },
  {
   "is_class": true,
   "is_explicit": false,
   "module": "nrv",
   "module_short": "nrv",
   "name": "axon"
  },
  {
   "is_class": true,
   "is_explicit": false,
   "module": "nrv.backend._NRV_Simulable",
   "module_short": "nrv",
   "name": "NRV_simulable"
  },
  {
   "is_class": true,
   "is_explicit": false,
   "module": "nrv.backend",
   "module_short": "nrv",
   "name": "NRV_simulable"
  },
  {
   "is_class": true,
   "is_explicit": false,
   "module": "nrv",
   "module_short": "nrv",
   "name": "NRV_simulable"
  },
  {
   "is_class": true,
   "is_explicit": false,
   "module": "nrv.backend._NRV_Class",
   "module_short": "nrv",
   "name": "NRV_class"
  },
  {
   "is_class": true,
   "is_explicit": false,
   "module": "nrv.backend",
   "module_short": "nrv",
   "name": "NRV_class"
  },
  {
   "is_class": true,
   "is_explicit": false,
   "module": "nrv",
   "module_short": "nrv",
   "name": "NRV_class"
  },
  {
   "is_class": false,
   "is_explicit": false,
   "module": "nrv",
   "module_short": "nrv",
   "name": "unmyelinated"
  }
 ],
 "nseg_per_l": [
  {
   "is_class": false,
   "is_explicit": false,
   "module": "builtins",
   "module_short": "builtins",
   "name": "int"
  }
 ],
 "plt.show": [
  {
   "is_class": false,
   "is_explicit": false,
   "module": "builtins",
   "module_short": "builtins",
   "name": "function"
  },
  {
   "is_class": false,
   "is_explicit": false,
   "module": "matplotlib.pyplot",
   "module_short": "matplotlib.pyplot",
   "name": "show"
  }
 ],
 "plt.subplots": [
  {
   "is_class": false,
   "is_explicit": false,
   "module": "builtins",
   "module_short": "builtins",
   "name": "function"
  },
  {
   "is_class": false,
   "is_explicit": false,
   "module": "matplotlib.pyplot",
   "module_short": "matplotlib.pyplot",
   "name": "subplots"
  }
 ],
 "results": [
  {
   "is_class": false,
   "is_explicit": false,
   "module": "nrv.nmod.results._unmyelinated_results",
   "module_short": "nrv.nmod.results",
   "name": "unmyelinated_results"
  },
  {
   "is_class": false,
   "is_explicit": false,
   "module": "nrv.nmod.results",
   "module_short": "nrv.nmod.results",
   "name": "unmyelinated_results"
  },
  {
   "is_class": false,
   "is_explicit": false,
   "module": "nrv.nmod",
   "module_short": "nrv.nmod",
   "name": "unmyelinated_results"
  },
  {
   "is_class": false,
   "is_explicit": false,
   "module": "nrv",
   "module_short": "nrv",
   "name": "unmyelinated_results"
  }
 ],
 "results.colormap_plot": [
  {
   "is_class": false,
   "is_explicit": false,
   "module": "nrv.nmod.results._unmyelinated_results",
   "module_short": "nrv.nmod.results",
   "name": "unmyelinated_results.colormap_plot"
  },
  {
   "is_class": false,
   "is_explicit": false,
   "module": "nrv.nmod.results",
   "module_short": "nrv.nmod.results",
   "name": "unmyelinated_results.colormap_plot"
  },
  {
   "is_class": false,
   "is_explicit": false,
   "module": "nrv.nmod",
   "module_short": "nrv.nmod",
   "name": "unmyelinated_results.colormap_plot"
  },
  {
   "is_class": false,
   "is_explicit": false,
   "module": "nrv",
   "module_short": "nrv",
   "name": "unmyelinated_results.colormap_plot"
  },
  {
   "is_class": false,
   "is_explicit": false,
   "module": "nrv.nmod.results._axons_results",
   "module_short": "nrv.nmod.results",
   "name": "axon_results.colormap_plot"
  },
  {
   "is_class": false,
   "is_explicit": false,
   "module": "nrv.nmod.results",
   "module_short": "nrv.nmod.results",
   "name": "axon_results.colormap_plot"
  },
  {
   "is_class": false,
   "is_explicit": false,
   "module": "nrv.nmod",
   "module_short": "nrv.nmod",
   "name": "axon_results.colormap_plot"
  },
  {
   "is_class": false,
   "is_explicit": false,
   "module": "nrv",
   "module_short": "nrv",
   "name": "axon_results.colormap_plot"
  },
  {
   "is_class": false,
   "is_explicit": false,
   "module": "nrv.backend._NRV_Results",
   "module_short": "nrv.backend._NRV_Results",
   "name": "sim_results.colormap_plot"
  },
  {
   "is_class": false,
   "is_explicit": false,
   "module": "nrv.backend",
   "module_short": "nrv.backend",
   "name": "sim_results.colormap_plot"
  },
  {
   "is_class": false,
   "is_explicit": false,
   "module": "nrv",
   "module_short": "nrv",
   "name": "sim_results.colormap_plot"
  },
  {
   "is_class": false,
   "is_explicit": false,
   "module": "nrv.backend._NRV_Results",
   "module_short": "nrv.backend._NRV_Results",
   "name": "NRV_results.colormap_plot"
  },
  {
   "is_class": false,
   "is_explicit": false,
   "module": "nrv.backend",
   "module_short": "nrv.backend",
   "name": "NRV_results.colormap_plot"
  },
  {
   "is_class": false,
   "is_explicit": false,
   "module": "nrv",
   "module_short": "nrv",
   "name": "NRV_results.colormap_plot"
  },
  {
   "is_class": false,
   "is_explicit": false,
   "module": "nrv.backend._NRV_Class",
   "module_short": "nrv.backend._NRV_Class",
   "name": "NRV_class.colormap_plot"
  },
  {
   "is_class": false,
   "is_explicit": false,
   "module": "nrv.backend",
   "module_short": "nrv.backend",
   "name": "NRV_class.colormap_plot"
  },
  {
   "is_class": false,
   "is_explicit": false,
   "module": "nrv",
   "module_short": "nrv",
   "name": "NRV_class.colormap_plot"
  },
  {
   "is_class": false,
   "is_explicit": false,
   "module": "builtins",
   "module_short": "builtins",
   "name": "dict.colormap_plot"
  }
 ],
 "results.count_APs": [
  {
   "is_class": false,
   "is_explicit": false,
   "module": "nrv.nmod.results._unmyelinated_results",
   "module_short": "nrv.nmod.results",
   "name": "unmyelinated_results.count_APs"
  },
  {
   "is_class": false,
   "is_explicit": false,
   "module": "nrv.nmod.results",
   "module_short": "nrv.nmod.results",
   "name": "unmyelinated_results.count_APs"
  },
  {
   "is_class": false,
   "is_explicit": false,
   "module": "nrv.nmod",
   "module_short": "nrv.nmod",
   "name": "unmyelinated_results.count_APs"
  },
  {
   "is_class": false,
   "is_explicit": false,
   "module": "nrv",
   "module_short": "nrv",
   "name": "unmyelinated_results.count_APs"
  },
  {
   "is_class": false,
   "is_explicit": false,
   "module": "nrv.nmod.results._axons_results",
   "module_short": "nrv.nmod.results",
   "name": "axon_results.count_APs"
  },
  {
   "is_class": false,
   "is_explicit": false,
   "module": "nrv.nmod.results",
   "module_short": "nrv.nmod.results",
   "name": "axon_results.count_APs"
  },
  {
   "is_class": false,
   "is_explicit": false,
   "module": "nrv.nmod",
   "module_short": "nrv.nmod",
   "name": "axon_results.count_APs"
  },
  {
   "is_class": false,
   "is_explicit": false,
   "module": "nrv",
   "module_short": "nrv",
   "name": "axon_results.count_APs"
  },
  {
   "is_class": false,
   "is_explicit": false,
   "module": "nrv.backend._NRV_Results",
   "module_short": "nrv.backend._NRV_Results",
   "name": "sim_results.count_APs"
  },
  {
   "is_class": false,
   "is_explicit": false,
   "module": "nrv.backend",
   "module_short": "nrv.backend",
   "name": "sim_results.count_APs"
  },
  {
   "is_class": false,
   "is_explicit": false,
   "module": "nrv",
   "module_short": "nrv",
   "name": "sim_results.count_APs"
  },
  {
   "is_class": false,
   "is_explicit": false,
   "module": "nrv.backend._NRV_Results",
   "module_short": "nrv.backend._NRV_Results",
   "name": "NRV_results.count_APs"
  },
  {
   "is_class": false,
   "is_explicit": false,
   "module": "nrv.backend",
   "module_short": "nrv.backend",
   "name": "NRV_results.count_APs"
  },
  {
   "is_class": false,
   "is_explicit": false,
   "module": "nrv",
   "module_short": "nrv",
   "name": "NRV_results.count_APs"
  },
  {
   "is_class": false,
   "is_explicit": false,
   "module": "nrv.backend._NRV_Class",
   "module_short": "nrv.backend._NRV_Class",
   "name": "NRV_class.count_APs"
  },
  {
   "is_class": false,
   "is_explicit": false,
   "module": "nrv.backend",
   "module_short": "nrv.backend",
   "name": "NRV_class.count_APs"
  },
  {
   "is_class": false,
   "is_explicit": false,
   "module": "nrv",
   "module_short": "nrv",
   "name": "NRV_class.count_APs"
  },
  {
   "is_class": false,
   "is_explicit": false,
   "module": "builtins",
   "module_short": "builtins",
   "name": "dict.count_APs"
  }
 ],
 "results.filter_freq": [
  {
   "is_class": false,
   "is_explicit": false,
   "module": "nrv.nmod.results._unmyelinated_results",
   "module_short": "nrv.nmod.results",
   "name": "unmyelinated_results.filter_freq"
  },
  {
   "is_class": false,
   "is_explicit": false,
   "module": "nrv.nmod.results",
   "module_short": "nrv.nmod.results",
   "name": "unmyelinated_results.filter_freq"
  },
  {
   "is_class": false,
   "is_explicit": false,
   "module": "nrv.nmod",
   "module_short": "nrv.nmod",
   "name": "unmyelinated_results.filter_freq"
  },
  {
   "is_class": false,
   "is_explicit": false,
   "module": "nrv",
   "module_short": "nrv",
   "name": "unmyelinated_results.filter_freq"
  },
  {
   "is_class": false,
   "is_explicit": false,
   "module": "nrv.nmod.results._axons_results",
   "module_short": "nrv.nmod.results",
   "name": "axon_results.filter_freq"
  },
  {
   "is_class": false,
   "is_explicit": false,
   "module": "nrv.nmod.results",
   "module_short": "nrv.nmod.results",
   "name": "axon_results.filter_freq"
  },
  {
   "is_class": false,
   "is_explicit": false,
   "module": "nrv.nmod",
   "module_short": "nrv.nmod",
   "name": "axon_results.filter_freq"
  },
  {
   "is_class": false,
   "is_explicit": false,
   "module": "nrv",
   "module_short": "nrv",
   "name": "axon_results.filter_freq"
  },
  {
   "is_class": false,
   "is_explicit": false,
   "module": "nrv.backend._NRV_Results",
   "module_short": "nrv",
   "name": "sim_results.filter_freq"
  },
  {
   "is_class": false,
   "is_explicit": false,
   "module": "nrv.backend",
   "module_short": "nrv",
   "name": "sim_results.filter_freq"
  },
  {
   "is_class": false,
   "is_explicit": false,
   "module": "nrv",
   "module_short": "nrv",
   "name": "sim_results.filter_freq"
  },
  {
   "is_class": false,
   "is_explicit": false,
   "module": "nrv.backend._NRV_Results",
   "module_short": "nrv.backend._NRV_Results",
   "name": "NRV_results.filter_freq"
  },
  {
   "is_class": false,
   "is_explicit": false,
   "module": "nrv.backend",
   "module_short": "nrv.backend",
   "name": "NRV_results.filter_freq"
  },
  {
   "is_class": false,
   "is_explicit": false,
   "module": "nrv",
   "module_short": "nrv",
   "name": "NRV_results.filter_freq"
  },
  {
   "is_class": false,
   "is_explicit": false,
   "module": "nrv.backend._NRV_Class",
   "module_short": "nrv.backend._NRV_Class",
   "name": "NRV_class.filter_freq"
  },
  {
   "is_class": false,
   "is_explicit": false,
   "module": "nrv.backend",
   "module_short": "nrv.backend",
   "name": "NRV_class.filter_freq"
  },
  {
   "is_class": false,
   "is_explicit": false,
   "module": "nrv",
   "module_short": "nrv",
   "name": "NRV_class.filter_freq"
  },
  {
   "is_class": false,
   "is_explicit": false,
   "module": "builtins",
   "module_short": "builtins",
   "name": "dict.filter_freq"
  }
 ],
 "results.plot_x_t": [
  {
   "is_class": false,
   "is_explicit": false,
   "module": "nrv.nmod.results._unmyelinated_results",
   "module_short": "nrv.nmod.results",
   "name": "unmyelinated_results.plot_x_t"
  },
  {
   "is_class": false,
   "is_explicit": false,
   "module": "nrv.nmod.results",
   "module_short": "nrv.nmod.results",
   "name": "unmyelinated_results.plot_x_t"
  },
  {
   "is_class": false,
   "is_explicit": false,
   "module": "nrv.nmod",
   "module_short": "nrv.nmod",
   "name": "unmyelinated_results.plot_x_t"
  },
  {
   "is_class": false,
   "is_explicit": false,
   "module": "nrv",
   "module_short": "nrv",
   "name": "unmyelinated_results.plot_x_t"
  },
  {
   "is_class": false,
   "is_explicit": false,
   "module": "nrv.nmod.results._axons_results",
   "module_short": "nrv.nmod.results",
   "name": "axon_results.plot_x_t"
  },
  {
   "is_class": false,
   "is_explicit": false,
   "module": "nrv.nmod.results",
   "module_short": "nrv.nmod.results",
   "name": "axon_results.plot_x_t"
  },
  {
   "is_class": false,
   "is_explicit": false,
   "module": "nrv.nmod",
   "module_short": "nrv.nmod",
   "name": "axon_results.plot_x_t"
  },
  {
   "is_class": false,
   "is_explicit": false,
   "module": "nrv",
   "module_short": "nrv",
   "name": "axon_results.plot_x_t"
  },
  {
   "is_class": false,
   "is_explicit": false,
   "module": "nrv.backend._NRV_Results",
   "module_short": "nrv.backend._NRV_Results",
   "name": "sim_results.plot_x_t"
  },
  {
   "is_class": false,
   "is_explicit": false,
   "module": "nrv.backend",
   "module_short": "nrv.backend",
   "name": "sim_results.plot_x_t"
  },
  {
   "is_class": false,
   "is_explicit": false,
   "module": "nrv",
   "module_short": "nrv",
   "name": "sim_results.plot_x_t"
  },
  {
   "is_class": false,
   "is_explicit": false,
   "module": "nrv.backend._NRV_Results",
   "module_short": "nrv.backend._NRV_Results",
   "name": "NRV_results.plot_x_t"
  },
  {
   "is_class": false,
   "is_explicit": false,
   "module": "nrv.backend",
   "module_short": "nrv.backend",
   "name": "NRV_results.plot_x_t"
  },
  {
   "is_class": false,
   "is_explicit": false,
   "module": "nrv",
   "module_short": "nrv",
   "name": "NRV_results.plot_x_t"
  },
  {
   "is_class": false,
   "is_explicit": false,
   "module": "nrv.backend._NRV_Class",
   "module_short": "nrv.backend._NRV_Class",
   "name": "NRV_class.plot_x_t"
  },
  {
   "is_class": false,
   "is_explicit": false,
   "module": "nrv.backend",
   "module_short": "nrv.backend",
   "name": "NRV_class.plot_x_t"
  },
  {
   "is_class": false,
   "is_explicit": false,
   "module": "nrv",
   "module_short": "nrv",
   "name": "NRV_class.plot_x_t"
  },
  {
   "is_class": false,
   "is_explicit": false,
   "module": "builtins",
   "module_short": "builtins",
   "name": "dict.plot_x_t"
  }
 ],
 "results.raster_plot": [
  {
   "is_class": false,
   "is_explicit": false,
   "module": "nrv.nmod.results._unmyelinated_results",
   "module_short": "nrv.nmod.results",
   "name": "unmyelinated_results.raster_plot"
  },
  {
   "is_class": false,
   "is_explicit": false,
   "module": "nrv.nmod.results",
   "module_short": "nrv.nmod.results",
   "name": "unmyelinated_results.raster_plot"
  },
  {
   "is_class": false,
   "is_explicit": false,
   "module": "nrv.nmod",
   "module_short": "nrv.nmod",
   "name": "unmyelinated_results.raster_plot"
  },
  {
   "is_class": false,
   "is_explicit": false,
   "module": "nrv",
   "module_short": "nrv",
   "name": "unmyelinated_results.raster_plot"
  },
  {
   "is_class": false,
   "is_explicit": false,
   "module": "nrv.nmod.results._axons_results",
   "module_short": "nrv.nmod.results",
   "name": "axon_results.raster_plot"
  },
  {
   "is_class": false,
   "is_explicit": false,
   "module": "nrv.nmod.results",
   "module_short": "nrv.nmod.results",
   "name": "axon_results.raster_plot"
  },
  {
   "is_class": false,
   "is_explicit": false,
   "module": "nrv.nmod",
   "module_short": "nrv.nmod",
   "name": "axon_results.raster_plot"
  },
  {
   "is_class": false,
   "is_explicit": false,
   "module": "nrv",
   "module_short": "nrv",
   "name": "axon_results.raster_plot"
  },
  {
   "is_class": false,
   "is_explicit": false,
   "module": "nrv.backend._NRV_Results",
   "module_short": "nrv.backend._NRV_Results",
   "name": "sim_results.raster_plot"
  },
  {
   "is_class": false,
   "is_explicit": false,
   "module": "nrv.backend",
   "module_short": "nrv.backend",
   "name": "sim_results.raster_plot"
  },
  {
   "is_class": false,
   "is_explicit": false,
   "module": "nrv",
   "module_short": "nrv",
   "name": "sim_results.raster_plot"
  },
  {
   "is_class": false,
   "is_explicit": false,
   "module": "nrv.backend._NRV_Results",
   "module_short": "nrv.backend._NRV_Results",
   "name": "NRV_results.raster_plot"
  },
  {
   "is_class": false,
   "is_explicit": false,
   "module": "nrv.backend",
   "module_short": "nrv.backend",
   "name": "NRV_results.raster_plot"
  },
  {
   "is_class": false,
   "is_explicit": false,
   "module": "nrv",
   "module_short": "nrv",
   "name": "NRV_results.raster_plot"
  },
  {
   "is_class": false,
   "is_explicit": false,
   "module": "nrv.backend._NRV_Class",
   "module_short": "nrv.backend._NRV_Class",
   "name": "NRV_class.raster_plot"
  },
  {
   "is_class": false,
   "is_explicit": false,
   "module": "nrv.backend",
   "module_short": "nrv.backend",
   "name": "NRV_class.raster_plot"
  },
  {
   "is_class": false,
   "is_explicit": false,
   "module": "nrv",
   "module_short": "nrv",
   "name": "NRV_class.raster_plot"
  },
  {
   "is_class": false,
   "is_explicit": false,
   "module": "builtins",
   "module_short": "builtins",
   "name": "dict.raster_plot"
  }
 ],
 "results.rasterize": [
  {
   "is_class": false,
   "is_explicit": false,
   "module": "nrv.nmod.results._unmyelinated_results",
   "module_short": "nrv.nmod.results",
   "name": "unmyelinated_results.rasterize"
  },
  {
   "is_class": false,
   "is_explicit": false,
   "module": "nrv.nmod.results",
   "module_short": "nrv.nmod.results",
   "name": "unmyelinated_results.rasterize"
  },
  {
   "is_class": false,
   "is_explicit": false,
   "module": "nrv.nmod",
   "module_short": "nrv.nmod",
   "name": "unmyelinated_results.rasterize"
  },
  {
   "is_class": false,
   "is_explicit": false,
   "module": "nrv",
   "module_short": "nrv",
   "name": "unmyelinated_results.rasterize"
  },
  {
   "is_class": false,
   "is_explicit": false,
   "module": "nrv.nmod.results._axons_results",
   "module_short": "nrv.nmod.results",
   "name": "axon_results.rasterize"
  },
  {
   "is_class": false,
   "is_explicit": false,
   "module": "nrv.nmod.results",
   "module_short": "nrv.nmod.results",
   "name": "axon_results.rasterize"
  },
  {
   "is_class": false,
   "is_explicit": false,
   "module": "nrv.nmod",
   "module_short": "nrv.nmod",
   "name": "axon_results.rasterize"
  },
  {
   "is_class": false,
   "is_explicit": false,
   "module": "nrv",
   "module_short": "nrv",
   "name": "axon_results.rasterize"
  },
  {
   "is_class": false,
   "is_explicit": false,
   "module": "nrv.backend._NRV_Results",
   "module_short": "nrv.backend._NRV_Results",
   "name": "sim_results.rasterize"
  },
  {
   "is_class": false,
   "is_explicit": false,
   "module": "nrv.backend",
   "module_short": "nrv.backend",
   "name": "sim_results.rasterize"
  },
  {
   "is_class": false,
   "is_explicit": false,
   "module": "nrv",
   "module_short": "nrv",
   "name": "sim_results.rasterize"
  },
  {
   "is_class": false,
   "is_explicit": false,
   "module": "nrv.backend._NRV_Results",
   "module_short": "nrv.backend._NRV_Results",
   "name": "NRV_results.rasterize"
  },
  {
   "is_class": false,
   "is_explicit": false,
   "module": "nrv.backend",
   "module_short": "nrv.backend",
   "name": "NRV_results.rasterize"
  },
  {
   "is_class": false,
   "is_explicit": false,
   "module": "nrv",
   "module_short": "nrv",
   "name": "NRV_results.rasterize"
  },
  {
   "is_class": false,
   "is_explicit": false,
   "module": "nrv.backend._NRV_Class",
   "module_short": "nrv.backend._NRV_Class",
   "name": "NRV_class.rasterize"
  },
  {
   "is_class": false,
   "is_explicit": false,
   "module": "nrv.backend",
   "module_short": "nrv.backend",
   "name": "NRV_class.rasterize"
  },
  {
   "is_class": false,
   "is_explicit": false,
   "module": "nrv",
   "module_short": "nrv",
   "name": "NRV_class.rasterize"
  },
  {
   "is_class": false,
   "is_explicit": false,
   "module": "builtins",
   "module_short": "builtins",
   "name": "dict.rasterize"
  }
 ],
 "results.x_rec": [
  {
   "is_class": false,
   "is_explicit": false,
   "module": "numpy",
   "module_short": "numpy",
   "name": "ndarray"
  }
 ],
 "stim_1": [
  {
   "is_class": false,
   "is_explicit": false,
   "module": "nrv.utils._stimulus",
   "module_short": "nrv",
   "name": "stimulus"
  },
  {
   "is_class": false,
   "is_explicit": false,
   "module": "nrv.utils",
   "module_short": "nrv",
   "name": "stimulus"
  },
  {
   "is_class": false,
   "is_explicit": false,
   "module": "nrv",
   "module_short": "nrv",
   "name": "stimulus"
  }
 ],
 "stim_1.sinus": [
  {
   "is_class": false,
   "is_explicit": false,
   "module": "nrv.utils._stimulus",
   "module_short": "nrv",
   "name": "stimulus.sinus"
  },
  {
   "is_class": false,
   "is_explicit": false,
   "module": "nrv.utils",
   "module_short": "nrv",
   "name": "stimulus.sinus"
  },
  {
   "is_class": false,
   "is_explicit": false,
   "module": "nrv",
   "module_short": "nrv",
   "name": "stimulus.sinus"
  },
  {
   "is_class": false,
   "is_explicit": false,
   "module": "nrv.backend._NRV_Class",
   "module_short": "nrv.backend._NRV_Class",
   "name": "NRV_class.sinus"
  },
  {
   "is_class": false,
   "is_explicit": false,
   "module": "nrv.backend",
   "module_short": "nrv.backend",
   "name": "NRV_class.sinus"
  },
  {
   "is_class": false,
   "is_explicit": false,
   "module": "nrv",
   "module_short": "nrv",
   "name": "NRV_class.sinus"
  }
 ],
 "stim_extra": [
  {
   "is_class": false,
   "is_explicit": false,
   "module": "nrv.fmod._extracellular",
   "module_short": "nrv",
   "name": "stimulation"
  },
  {
   "is_class": false,
   "is_explicit": false,
   "module": "nrv.fmod",
   "module_short": "nrv",
   "name": "stimulation"
  },
  {
   "is_class": false,
   "is_explicit": false,
   "module": "nrv",
   "module_short": "nrv",
   "name": "stimulation"
  }
 ],
 "stim_extra.add_electrode": [
  {
   "is_class": false,
   "is_explicit": false,
   "module": "nrv.fmod._extracellular",
   "module_short": "nrv",
   "name": "stimulation.add_electrode"
  },
  {
   "is_class": false,
   "is_explicit": false,
   "module": "nrv.fmod",
   "module_short": "nrv",
   "name": "stimulation.add_electrode"
  },
  {
   "is_class": false,
   "is_explicit": false,
   "module": "nrv",
   "module_short": "nrv",
   "name": "stimulation.add_electrode"
  },
  {
   "is_class": false,
   "is_explicit": false,
   "module": "nrv.fmod._extracellular",
   "module_short": "nrv",
   "name": "extracellular_context.add_electrode"
  },
  {
   "is_class": false,
   "is_explicit": false,
   "module": "nrv.fmod",
   "module_short": "nrv",
   "name": "extracellular_context.add_electrode"
  },
  {
   "is_class": false,
   "is_explicit": false,
   "module": "nrv",
   "module_short": "nrv",
   "name": "extracellular_context.add_electrode"
  },
  {
   "is_class": false,
   "is_explicit": false,
   "module": "nrv.backend._NRV_Class",
   "module_short": "nrv.backend._NRV_Class",
   "name": "NRV_class.add_electrode"
  },
  {
   "is_class": false,
   "is_explicit": false,
   "module": "nrv.backend",
   "module_short": "nrv.backend",
   "name": "NRV_class.add_electrode"
  },
  {
   "is_class": false,
   "is_explicit": false,
   "module": "nrv",
   "module_short": "nrv",
   "name": "NRV_class.add_electrode"
  }
 ],
 "t_amplitude": [
  {
   "is_class": false,
   "is_explicit": false,
   "module": "builtins",
   "module_short": "builtins",
   "name": "int"
  }
 ],
 "t_duration": [
  {
   "is_class": false,
   "is_explicit": false,
   "module": "builtins",
   "module_short": "builtins",
   "name": "int"
  }
 ],
 "t_position": [
  {
   "is_class": false,
   "is_explicit": false,
   "module": "builtins",
   "module_short": "builtins",
   "name": "float"
  }
 ],
 "t_sim": [
  {
   "is_class": false,
   "is_explicit": false,
   "module": "builtins",
   "module_short": "builtins",
   "name": "int"
  }
 ],
 "t_start": [
  {
   "is_class": false,
   "is_explicit": false,
   "module": "builtins",
   "module_short": "builtins",
   "name": "int"
  }
 ],
 "x_elec": [
  {
   "is_class": false,
   "is_explicit": false,
   "module": "builtins",
   "module_short": "builtins",
   "name": "float"
  }
 ],
 "y": [
  {
   "is_class": false,
   "is_explicit": false,
   "module": "builtins",
   "module_short": "builtins",
   "name": "int"
  }
 ],
 "y_elec": [
  {
   "is_class": false,
   "is_explicit": false,
   "module": "builtins",
   "module_short": "builtins",
   "name": "int"
  }
 ],
 "z": [
  {
   "is_class": false,
   "is_explicit": false,
   "module": "builtins",
   "module_short": "builtins",
   "name": "int"
  }
 ],
 "z_elec": [
  {
   "is_class": false,
   "is_explicit": false,
   "module": "builtins",
   "module_short": "builtins",
   "name": "int"
  }
 ]
}